{"0": {"schema_name": "qcschema_molecule", "schema_version": 2, "validated": true, "symbols": ["C", "C", "O", "H", "H", "H", "H"], "geometry": [0.0, 0.0, 0.0, 3.37200524, 0.0, 0.0, 1.27611659, 0.0, -2.05853304, -2.64135234, -0.46794743, 1.42911552, 4.11043773, -2.7819536, -0.62740573, 3.98838215, 1.04533702, 0.60941247, 4.87025897, -0.04087491, -1.59802719], "name": "C2H4O", "molecular_charge": 0.0, "molecular_multiplicity": 1, "fix_com": false, "fix_orientation": false, "provenance": {"creator": "QCElemental", "version": "0.28.0", "routine": "qcelemental.molparse.from_schema"}, "extras": {"notes": {}}}, "1": {"schema_name": "qcschema_molecule", "schema_version": 2, "validated": true, "symbols": ["C", "C", "O", "H", "H", "H", "H"], "geometry": [0.0, 0.0, 0.0, 3.18793197, 0.0, 0.0, -6.7230881, 0.0, -4.64779057, -1.06427997, -0.58173759, 2.26348232, 3.86782892, -1.24012634, 1.14450147, 4.68716708, 0.74418415, 1.49733745, 3.67922436, 0.83145548, -1.83794272], "name": "C2H4O", "molecular_charge": 0.0, "molecular_multiplicity": 1, "fix_com": false, "fix_orientation": false, "provenance": {"creator": "QCElemental", "version": "0.28.0", "routine": "qcelemental.molparse.from_schema"}, "extras": {"notes": {}}}, "2": {"schema_name": "qcschema_molecule", "schema_version": 2, "validated": true, "symbols": ["C", "C", "O", "H", "H", "H", "H"], "geometry": [0.0, 0.0, 0.0, 3.12253385, 0.0, 0.0, -0.77602319, 0.0, -2.62337189, -4.30729155, -0.82116894, 4.26560737, 4.63747843, -2.03922593, 1.03895106, 4.54749995, 1.44379764, 1.38265176, 3.45560145, 0.52394633, -3.12875043], "name": "C2H4O", "molecular_charge": 0.0, "molecular_multiplicity": 1, "fix_com": false, "fix_orientation": false, "provenance": {"creator": "QCElemental", "version": "0.28.0", "routine": "qcelemental.molparse.from_schema"}, "extras": {"notes": {}}}, "3": {"schema_name": "qcschema_molecule", "schema_version": 2, "validated": true, "symbols": ["C", "C", "O", "H", "H", "H", "H"], "geometry": [0.0, 0.0, 0.0, 2.75858186, 0.0, 0.0, -2.07326907, 0.0, -1.48166836, -1.30614936, 1.70168083, 8.09755135, 2.33277399, -1.60352397, -0.29198731, 3.95630439, 2.73486535, 0.19770866, 3.01851942, 0.53636705, -1.44070798], "name": "C2H4O", "molecular_charge": 0.0, "molecular_multiplicity": 1, "fix_com": false, "fix_orientation": false, "provenance": {"creator": "QCElemental", "version": "0.28.0", "routine": "qcelemental.molparse.from_schema"}, "extras": {"notes": {}}}, "4": {"schema_name": "qcschema_molecule", "schema_version": 2, "validated": true, "symbols": ["C", "C", "O", "H", "H", "H", "H"], "geometry": [0.0, 0.0, 0.0, 3.49867346, 0.0, 0.0, -1.06317783, 0.0, -1.57303418, -0.6920246, 0.43499525, 2.29510589, 9.65931154, -4.73433506, 3.76900612, 5.70584664, 0.87188038, 0.21615485, 3.93649051, -0.10732961, -2.90585862], "name": "C2H4O", "molecular_charge": 0.0, "molecular_multiplicity": 1, "fix_com": false, "fix_orientation": false, "provenance": {"creator": "QCElemental", "version": "0.28.0", "routine": "qcelemental.molparse.from_schema"}, "extras": {"notes": {}}}, "5": {"schema_name": "qcschema_molecule", "schema_version": 2, "validated": true, "symbols": ["C", "C", "O", "H", "H", "H", "H"], "geometry": [0.0, 0.0, 0.0, 7.70223004, 0.0, 0.0, -0.74791574, 0.0, -1.7291133, -1.19190473, -0.55963759, 0.53226086, 7.69874074, -1.85415448, -0.52157627, 9.00859847, -0.11679247, 1.27828405, 8.70994931, 0.83817524, -0.79284521], "name": "C2H4O", "molecular_charge": 0.0, "molecular_multiplicity": 1, "fix_com": false, "fix_orientation": false, "provenance": {"creator": "QCElemental", "version": "0.28.0", "routine": "qcelemental.molparse.from_schema"}, "extras": {"notes": {}}}, "6": {"schema_name": "qcschema_molecule", "schema_version": 2, "validated": true, "symbols": ["C", "C", "O", "H", "H", "H", "H"], "geometry": [0.0, 0.0, 0.0, 2.83790384, 0.0, 0.0, -1.5852941, 0.0, -0.49250567, -1.74665978, -2.74648008, 5.07335321, 4.0266696, -2.12088879, 0.54673491, 3.52156343, 0.18283462, 1.32840462, 3.95311162, 0.42054927, -1.77047848], "name": "C2H4O", "molecular_charge": 0.0, "molecular_multiplicity": 1, "fix_com": false, "fix_orientation": false, "provenance": {"creator": "QCElemental", "version": "0.28.0", "routine": "qcelemental.molparse.from_schema"}, "extras": {"notes": {}}}, "7": {"schema_name": "qcschema_molecule", "schema_version": 2, "validated": true, "symbols": ["C", "C", "O", "H", "H", "H", "H"], "geometry": [0.0, 0.0, 0.0, 4.23552996, 0.0, 0.0, -0.64235007, 0.0, -3.25527609, -0.61520231, 0.19574832, 2.53057728, 4.71401349, -0.3563904, 2.21671017, 5.31286086, 1.38956113, 0.74409331, 4.82886628, -0.0660585, -1.12226722], "name": "C2H4O", "molecular_charge": 0.0, "molecular_multiplicity": 1, "fix_com": false, "fix_orientation": false, "provenance": {"creator": "QCElemental", "version": "0.28.0", "routine": "qcelemental.molparse.from_schema"}, "extras": {"notes": {}}}, "8": {"schema_name": "qcschema_molecule", "schema_version": 2, "validated": true, "symbols": ["C", "C", "O", "H", "H", "H", "H"], "geometry": [0.0, 0.0, 0.0, 5.22843292, 0.0, 0.0, -0.69818286, 0.0, -2.21782934, -0.96589446, -0.94201616, 1.90482689, 5.15244223, -1.57961699, 0.2786851, 5.36044248, 0.32620685, 2.0890109, 5.1016136, 1.48773769, -0.87174905], "name": "C2H4O", "molecular_charge": 0.0, "molecular_multiplicity": 1, "fix_com": false, "fix_orientation": false, "provenance": {"creator": "QCElemental", "version": "0.28.0", "routine": "qcelemental.molparse.from_schema"}, "extras": {"notes": {}}}, "9": {"schema_name": "qcschema_molecule", "schema_version": 2, "validated": true, "symbols": ["C", "C", "O", "H", "H", "H", "H"], "geometry": [0.0, 0.0, 0.0, 13.56646718, 0.0, 0.0, -0.98440016, 0.0, -1.59229392, -1.3889396, 0.09585168, 1.19586675, 14.46859279, -1.64473603, 1.12876126, 12.70573628, 1.78543396, 0.55560957, 14.69559717, 0.50850434, -1.80922104], "name": "C2H4O", "molecular_charge": 0.0, "molecular_multiplicity": 1, "fix_com": false, "fix_orientation": false, "provenance": {"creator": "QCElemental", "version": "0.28.0", "routine": "qcelemental.molparse.from_schema"}, "extras": {"notes": {}}}, "10": {"schema_name": "qcschema_molecule", "schema_version": 2, "validated": true, "symbols": ["C", "C", "O", "H", "H", "H", "H"], "geometry": [0.0, 0.0, 0.0, 1.80239145, 0.0, 0.0, -0.72389002, 0.0, -2.37367051, 0.43964454, -0.66102604, 1.88009748, 2.37589062, -1.37536958, 0.57706723, 4.44336677, -0.00121978, 1.76630119, 3.23360094, 0.23472853, -1.72297823], "name": "C2H4O", "molecular_charge": 0.0, "molecular_multiplicity": 1, "fix_com": false, "fix_orientation": false, "provenance": {"creator": "QCElemental", "version": "0.28.0", "routine": "qcelemental.molparse.from_schema"}, "extras": {"notes": {}}}, "11": {"schema_name": "qcschema_molecule", "schema_version": 2, "validated": true, "symbols": ["C", "C", "O", "H", "H", "H", "H"], "geometry": [0.0, 0.0, 0.0, 4.00748181, 0.0, 0.0, -0.54004449, 0.0, -2.86120621, -1.62774391, -0.65429009, 1.58936435, 5.64909654, -1.6911263, 0.45825507, 5.08787043, 1.15606628, 0.38261663, 2.85523267, 1.20508833, -1.38933507], "name": "C2H4O", "molecular_charge": 0.0, "molecular_multiplicity": 1, "fix_com": false, "fix_orientation": false, "provenance": {"creator": "QCElemental", "version": "0.28.0", "routine": "qcelemental.molparse.from_schema"}, "extras": {"notes": {}}}, "12": {"schema_name": "qcschema_molecule", "schema_version": 2, "validated": true, "symbols": ["C", "C", "O", "H", "H", "H", "H"], "geometry": [0.0, 0.0, 0.0, 3.6445176, 0.0, 0.0, 0.21400081, 0.0, -1.98143032, -0.17255263, -0.82079126, 2.7527101, 3.87419655, -1.23911979, 0.52354123, 5.22203993, 0.72968311, 0.95011502, 5.21649868, 1.38921308, -2.59348792], "name": "C2H4O", "molecular_charge": 0.0, "molecular_multiplicity": 1, "fix_com": false, "fix_orientation": false, "provenance": {"creator": "QCElemental", "version": "0.28.0", "routine": "qcelemental.molparse.from_schema"}, "extras": {"notes": {}}}, "13": {"schema_name": "qcschema_molecule", "schema_version": 2, "validated": true, "symbols": ["C", "C", "O", "H", "H", "H", "H"], "geometry": [0.0, 0.0, 0.0, 4.06632657, 0.0, 0.0, -2.28242906, 0.0, -3.42880653, -1.04974351, 0.04609554, 2.77166994, 4.29956055, -1.40780501, 1.09468083, 5.54895067, 1.29852784, 0.42015633, 4.21337747, -0.74327078, -1.27706148], "name": "C2H4O", "molecular_charge": 0.0, "molecular_multiplicity": 1, "fix_com": false, "fix_orientation": false, "provenance": {"creator": "QCElemental", "version": "0.28.0", "routine": "qcelemental.molparse.from_schema"}, "extras": {"notes": {}}}, "14": {"schema_name": "qcschema_molecule", "schema_version": 2, "validated": true, "symbols": ["C", "C", "O", "H", "H", "H", "H"], "geometry": [0.0, 0.0, 0.0, 2.63717227, 0.0, 0.0, -1.10453396, 0.0, -0.88991764, -0.47750177, 0.00887179, 4.06956336, 2.63627278, -2.04378982, 0.16965029, 3.81426777, 1.83905509, 0.39968242, 2.07719045, 0.64009304, -1.54735176], "name": "C2H4O", "molecular_charge": 0.0, "molecular_multiplicity": 1, "fix_com": false, "fix_orientation": false, "provenance": {"creator": "QCElemental", "version": "0.28.0", "routine": "qcelemental.molparse.from_schema"}, "extras": {"notes": {}}}, "15": {"schema_name": "qcschema_molecule", "schema_version": 2, "validated": true, "symbols": ["C", "C", "O", "H", "H", "H", "H"], "geometry": [0.0, 0.0, 0.0, 3.29974249, 0.0, 0.0, -2.62871587, 0.0, -1.2311965, -1.20114796, -0.73654135, 1.13416116, 3.90752632, -1.67908719, -0.0696494, 3.35490242, 1.05916115, 2.4993117, 3.89554738, 1.93165932, -2.21547235], "name": "C2H4O", "molecular_charge": 0.0, "molecular_multiplicity": 1, "fix_com": false, "fix_orientation": false, "provenance": {"creator": "QCElemental", "version": "0.28.0", "routine": "qcelemental.molparse.from_schema"}, "extras": {"notes": {}}}, "16": {"schema_name": "qcschema_molecule", "schema_version": 2, "validated": true, "symbols": ["C", "C", "O", "H", "H", "H", "H"], "geometry": [0.0, 0.0, 0.0, 5.75678655, 0.0, 0.0, -1.29255294, 0.0, -1.91772659, -1.46200494, 0.39018956, 2.29333723, 7.02508733, -0.29803556, 0.68491016, 5.93212828, 1.46007222, 0.4624256, 4.87327675, -1.29878466, -1.37992194], "name": "C2H4O", "molecular_charge": 0.0, "molecular_multiplicity": 1, "fix_com": false, "fix_orientation": false, "provenance": {"creator": "QCElemental", "version": "0.28.0", "routine": "qcelemental.molparse.from_schema"}, "extras": {"notes": {}}}, "17": {"schema_name": "qcschema_molecule", "schema_version": 2, "validated": true, "symbols": ["C", "C", "O", "H", "H", "H", "H"], "geometry": [0.0, 0.0, 0.0, 3.1520754, 0.0, 0.0, -1.59571587, 0.0, -2.67017262, -0.0929947, -1.25251526, 1.97588393, 5.42462911, -0.28713241, -0.51177838, 3.76408227, -0.37017713, 2.30889986, 3.73925007, 0.7351373, -1.0981861], "name": "C2H4O", "molecular_charge": 0.0, "molecular_multiplicity": 1, "fix_com": false, "fix_orientation": false, "provenance": {"creator": "QCElemental", "version": "0.28.0", "routine": "qcelemental.molparse.from_schema"}, "extras": {"notes": {}}}, "18": {"schema_name": "qcschema_molecule", "schema_version": 2, "validated": true, "symbols": ["C", "C", "O", "H", "H", "H", "H"], "geometry": [0.0, 0.0, 0.0, 2.05308868, 0.0, 0.0, -3.35539962, 0.0, -1.57506037, -0.9384562, 0.21743385, 2.96795578, 1.40698864, -2.28116173, 0.06643434, 3.96229207, 2.13796803, -0.15160459, 1.42028425, 1.86725333, -1.97788654], "name": "C2H4O", "molecular_charge": 0.0, "molecular_multiplicity": 1, "fix_com": false, "fix_orientation": false, "provenance": {"creator": "QCElemental", "version": "0.28.0", "routine": "qcelemental.molparse.from_schema"}, "extras": {"notes": {}}}, "19": {"schema_name": "qcschema_molecule", "schema_version": 2, "validated": true, "symbols": ["C", "C", "O", "H", "H", "H", "H"], "geometry": [0.0, 0.0, 0.0, 4.50575473, 0.0, 0.0, -2.11061682, 0.0, -1.22443237, -0.5947741, -0.54317151, 1.7070651, 4.80339417, -1.75506251, 0.29393999, 2.8484618, 2.25196588, 0.61436715, 6.23845234, 0.33695638, -0.82293462], "name": "C2H4O", "molecular_charge": 0.0, "molecular_multiplicity": 1, "fix_com": false, "fix_orientation": false, "provenance": {"creator": "QCElemental", "version": "0.28.0", "routine": "qcelemental.molparse.from_schema"}, "extras": {"notes": {}}}, "20": {"schema_name": "qcschema_molecule", "schema_version": 2, "validated": true, "symbols": ["C", "C", "O", "H", "H", "H", "H"], "geometry": [0.0, 0.0, 0.0, 2.23349766, 0.0, 0.0, -2.43201016, 0.0, -1.0188932, -1.26425516, -1.10556439, 1.65516599, 2.49690271, -1.82829738, 0.68196471, 2.27524506, 0.64233051, 1.45136708, 2.39450179, 0.65021714, -1.26637655], "name": "C2H4O", "molecular_charge": 0.0, "molecular_multiplicity": 1, "fix_com": false, "fix_orientation": false, "provenance": {"creator": "QCElemental", "version": "0.28.0", "routine": "qcelemental.molparse.from_schema"}, "extras": {"notes": {}}}, "21": {"schema_name": "qcschema_molecule", "schema_version": 2, "validated": true, "symbols": ["C", "C", "O", "H", "H", "H", "H"], "geometry": [0.0, 0.0, 0.0, 3.21049593, 0.0, 0.0, -1.85651544, 0.0, -1.86343949, -0.65576526, 0.65384366, 1.42997048, 3.31781107, -2.82843058, 1.08080204, 4.64771353, 1.0312833, -0.08087995, 4.50710859, -0.54664927, -1.73016822], "name": "C2H4O", "molecular_charge": 0.0, "molecular_multiplicity": 1, "fix_com": false, "fix_orientation": false, "provenance": {"creator": "QCElemental", "version": "0.28.0", "routine": "qcelemental.molparse.from_schema"}, "extras": {"notes": {}}}, "22": {"schema_name": "qcschema_molecule", "schema_version": 2, "validated": true, "symbols": ["C", "C", "O", "H", "H", "H", "H"], "geometry": [0.0, 0.0, 0.0, 3.84378058, 0.0, 0.0, -0.28898386, 0.0, -1.56405532, -7.03068412, -2.834248, 3.09381938, 4.68500625, -2.11043737, -0.24033137, 5.03902118, 1.29436538, 2.08955421, 3.76788745, 0.41167635, -1.54265312], "name": "C2H4O", "molecular_charge": 0.0, "molecular_multiplicity": 1, "fix_com": false, "fix_orientation": false, "provenance": {"creator": "QCElemental", "version": "0.28.0", "routine": "qcelemental.molparse.from_schema"}, "extras": {"notes": {}}}, "23": {"schema_name": "qcschema_molecule", "schema_version": 2, "validated": true, "symbols": ["C", "C", "O", "H", "H", "H", "H"], "geometry": [0.0, 0.0, 0.0, 4.07153382, 0.0, 0.0, -1.15628495, 0.0, -1.51201285, -1.23947164, 0.0373027, 1.80868844, 4.3777788, -2.82651999, 0.7435244, 3.55138893, 0.92034268, 1.19355355, 5.03205906, 0.05073931, -1.32012682], "name": "C2H4O", "molecular_charge": 0.0, "molecular_multiplicity": 1, "fix_com": false, "fix_orientation": false, "provenance": {"creator": "QCElemental", "version": "0.28.0", "routine": "qcelemental.molparse.from_schema"}, "extras": {"notes": {}}}, "24": {"schema_name": "qcschema_molecule", "schema_version": 2, "validated": true, "symbols": ["C", "C", "O", "H", "H", "H", "H"], "geometry": [0.0, 0.0, 0.0, 3.79626689, 0.0, 0.0, -1.01635693, 0.0, -1.34699138, -0.13651127, -1.53197579, 1.65321372, 4.46444674, -2.16525367, -0.61417387, 4.36853382, -0.46432262, 1.72659201, 4.38548439, 1.28835302, -0.6918491], "name": "C2H4O", "molecular_charge": 0.0, "molecular_multiplicity": 1, "fix_com": false, "fix_orientation": false, "provenance": {"creator": "QCElemental", "version": "0.28.0", "routine": "qcelemental.molparse.from_schema"}, "extras": {"notes": {}}}, "25": {"schema_name": "qcschema_molecule", "schema_version": 2, "validated": true, "symbols": ["C", "C", "O", "H", "H", "H", "H"], "geometry": [0.0, 0.0, 0.0, 2.81746247, 0.0, 0.0, 0.61281383, 0.0, -1.74801321, -1.36348687, 0.34929859, 1.35286484, 4.39048533, -0.14670381, 0.12691067, 2.83931998, 2.00850906, -0.25691344, 3.37658347, -0.59798389, -1.52451901], "name": "C2H4O", "molecular_charge": 0.0, "molecular_multiplicity": 1, "fix_com": false, "fix_orientation": false, "provenance": {"creator": "QCElemental", "version": "0.28.0", "routine": "qcelemental.molparse.from_schema"}, "extras": {"notes": {}}}, "26": {"schema_name": "qcschema_molecule", "schema_version": 2, "validated": true, "symbols": ["C", "C", "O", "H", "H", "H", "H"], "geometry": [0.0, 0.0, 0.0, 2.82850519, 0.0, 0.0, -1.41854341, 0.0, -0.97493114, -0.52534506, -1.89109789, 0.94806772, 3.64069448, -1.60752894, 0.06135817, 3.70329763, 0.05660656, 1.10967265, 2.04153244, 2.40049465, -0.31389566], "name": "C2H4O", "molecular_charge": 0.0, "molecular_multiplicity": 1, "fix_com": false, "fix_orientation": false, "provenance": {"creator": "QCElemental", "version": "0.28.0", "routine": "qcelemental.molparse.from_schema"}, "extras": {"notes": {}}}, "27": {"schema_name": "qcschema_molecule", "schema_version": 2, "validated": true, "symbols": ["C", "C", "O", "H", "H", "H", "H"], "geometry": [0.0, 0.0, 0.0, 2.59931472, 0.0, 0.0, -1.87828041, 0.0, -0.51513164, -1.54884605, -1.64008099, 0.77602285, 3.62897077, -2.04744069, 0.13642043, 3.52882224, -0.51938579, 1.95976908, 3.63722483, 0.66161167, -0.86019588], "name": "C2H4O", "molecular_charge": 0.0, "molecular_multiplicity": 1, "fix_com": false, "fix_orientation": false, "provenance": {"creator": "QCElemental", "version": "0.28.0", "routine": "qcelemental.molparse.from_schema"}, "extras": {"notes": {}}}, "28": {"schema_name": "qcschema_molecule", "schema_version": 2, "validated": true, "symbols": ["C", "C", "O", "H", "H", "H", "H"], "geometry": [0.0, 0.0, 0.0, 2.78323583, 0.0, 0.0, -1.1043409, 0.0, -2.46078764, -0.62728111, -0.29597843, 1.83087263, 4.30504193, -4.34923556, 1.04656119, 4.30388227, 0.77106367, 1.21156111, 3.61717153, 0.38522002, -1.00130075], "name": "C2H4O", "molecular_charge": 0.0, "molecular_multiplicity": 1, "fix_com": false, "fix_orientation": false, "provenance": {"creator": "QCElemental", "version": "0.28.0", "routine": "qcelemental.molparse.from_schema"}, "extras": {"notes": {}}}, "29": {"schema_name": "qcschema_molecule", "schema_version": 2, "validated": true, "symbols": ["C", "C", "O", "H", "H", "H", "H"], "geometry": [0.0, 0.0, 0.0, 3.06978024, 0.0, 0.0, -0.69974118, 0.0, -1.58823811, -2.30708602, -0.31799337, 1.95866198, 2.21110067, -1.92262292, 0.61149787, 2.64202654, 1.28573458, 0.5056617, 2.73356068, 0.7414957, -1.5471432], "name": "C2H4O", "molecular_charge": 0.0, "molecular_multiplicity": 1, "fix_com": false, "fix_orientation": false, "provenance": {"creator": "QCElemental", "version": "0.28.0", "routine": "qcelemental.molparse.from_schema"}, "extras": {"notes": {}}}, "30": {"schema_name": "qcschema_molecule", "schema_version": 2, "validated": true, "symbols": ["C", "C", "O", "H", "H", "H", "H"], "geometry": [0.0, 0.0, 0.0, 2.95958596, 0.0, 0.0, 0.47666233, 0.0, -3.01740144, -1.58900097, 0.21963629, 0.99498014, 6.17337798, -5.25614283, 6.98424536, 3.16789197, 0.8960498, 0.92307544, 2.98258944, -0.26913923, -1.7960267], "name": "C2H4O", "molecular_charge": 0.0, "molecular_multiplicity": 1, "fix_com": false, "fix_orientation": false, "provenance": {"creator": "QCElemental", "version": "0.28.0", "routine": "qcelemental.molparse.from_schema"}, "extras": {"notes": {}}}, "31": {"schema_name": "qcschema_molecule", "schema_version": 2, "validated": true, "symbols": ["C", "C", "O", "H", "H", "H", "H"], "geometry": [0.0, 0.0, 0.0, 2.59343958, 0.0, 0.0, -0.42154478, 0.0, -2.95561679, -0.45096735, 0.22957912, 1.80325979, 3.65663878, -0.71788853, 0.39762974, 2.48424105, 1.43638001, 0.0735845, 2.87783669, 0.51342709, -3.1812925], "name": "C2H4O", "molecular_charge": 0.0, "molecular_multiplicity": 1, "fix_com": false, "fix_orientation": false, "provenance": {"creator": "QCElemental", "version": "0.28.0", "routine": "qcelemental.molparse.from_schema"}, "extras": {"notes": {}}}, "32": {"schema_name": "qcschema_molecule", "schema_version": 2, "validated": true, "symbols": ["C", "C", "O", "H", "H", "H", "H"], "geometry": [0.0, 0.0, 0.0, 4.67601721, 0.0, 0.0, -1.25160161, 0.0, -1.98181587, -1.30416426, 0.7104412, 1.19052499, 6.00745963, -0.93424235, 2.16617193, 6.0337137, 1.10915329, 0.55786084, 6.12617428, -1.64873493, -1.71182081], "name": "C2H4O", "molecular_charge": 0.0, "molecular_multiplicity": 1, "fix_com": false, "fix_orientation": false, "provenance": {"creator": "QCElemental", "version": "0.28.0", "routine": "qcelemental.molparse.from_schema"}, "extras": {"notes": {}}}, "33": {"schema_name": "qcschema_molecule", "schema_version": 2, "validated": true, "symbols": ["C", "C", "O", "H", "H", "H", "H"], "geometry": [0.0, 0.0, 0.0, 3.46350372, 0.0, 0.0, -1.56584844, 0.0, -1.21735795, -1.25937297, -0.90334343, 2.26416221, 5.93463402, -5.73540555, 1.72112236, 3.47838632, 0.65896866, 1.18306657, 4.87609171, 1.17876849, -1.4254129], "name": "C2H4O", "molecular_charge": 0.0, "molecular_multiplicity": 1, "fix_com": false, "fix_orientation": false, "provenance": {"creator": "QCElemental", "version": "0.28.0", "routine": "qcelemental.molparse.from_schema"}, "extras": {"notes": {}}}, "34": {"schema_name": "qcschema_molecule", "schema_version": 2, "validated": true, "symbols": ["C", "C", "O", "H", "H", "H", "H"], "geometry": [0.0, 0.0, 0.0, 1.86911385, 0.0, 0.0, -1.53415213, 0.0, -0.57985001, -1.28188584, -0.19717558, 2.78367319, 5.91741416, -11.68421053, 3.25891881, 3.6485138, 1.24279662, 0.32649264, 2.79836614, -0.82382673, -1.79993792], "name": "C2H4O", "molecular_charge": 0.0, "molecular_multiplicity": 1, "fix_com": false, "fix_orientation": false, "provenance": {"creator": "QCElemental", "version": "0.28.0", "routine": "qcelemental.molparse.from_schema"}, "extras": {"notes": {}}}, "35": {"schema_name": "qcschema_molecule", "schema_version": 2, "validated": true, "symbols": ["C", "C", "O", "H", "H", "H", "H"], "geometry": [0.0, 0.0, 0.0, 5.36386267, 0.0, 0.0, -2.03395014, 0.0, -1.21988314, -1.19831506, -0.74939446, 0.83718957, 7.19194297, -1.45840086, 0.43041024, 5.12349934, 1.9202761, 1.59467413, 5.5852773, 1.12299098, -1.47653463], "name": "C2H4O", "molecular_charge": 0.0, "molecular_multiplicity": 1, "fix_com": false, "fix_orientation": false, "provenance": {"creator": "QCElemental", "version": "0.28.0", "routine": "qcelemental.molparse.from_schema"}, "extras": {"notes": {}}}, "36": {"schema_name": "qcschema_molecule", "schema_version": 2, "validated": true, "symbols": ["C", "C", "O", "H", "H", "H", "H"], "geometry": [0.0, 0.0, 0.0, 3.51907462, 0.0, 0.0, -1.07179947, 0.0, -1.47980857, -0.37610564, 0.76849695, 1.38779655, 4.39148568, -2.90009874, 1.11886806, 4.28557513, 1.33331922, -0.29828912, 4.35359201, -0.77838526, -1.00786422], "name": "C2H4O", "molecular_charge": 0.0, "molecular_multiplicity": 1, "fix_com": false, "fix_orientation": false, "provenance": {"creator": "QCElemental", "version": "0.28.0", "routine": "qcelemental.molparse.from_schema"}, "extras": {"notes": {}}}, "37": {"schema_name": "qcschema_molecule", "schema_version": 2, "validated": true, "symbols": ["C", "C", "O", "H", "H", "H", "H"], "geometry": [0.0, 0.0, 0.0, 3.15991916, 0.0, 0.0, -1.36813837, 0.0, -1.60094065, -1.53431257, 0.19549651, 0.91020041, 4.04732, -3.25366804, 1.97806257, 3.23053873, 1.81174308, -0.0933956, 3.58367599, -0.63613689, -2.0461199], "name": "C2H4O", "molecular_charge": 0.0, "molecular_multiplicity": 1, "fix_com": false, "fix_orientation": false, "provenance": {"creator": "QCElemental", "version": "0.28.0", "routine": "qcelemental.molparse.from_schema"}, "extras": {"notes": {}}}, "38": {"schema_name": "qcschema_molecule", "schema_version": 2, "validated": true, "symbols": ["C", "C", "O", "H", "H", "H", "H"], "geometry": [0.0, 0.0, 0.0, 4.14409063, 0.0, 0.0, -5.55001487, 0.0, -1.42762337, -0.27105326, 0.10120093, 2.38365638, 4.29695598, -1.3753479, 1.02554469, 4.28310307, 1.015691, 2.06837526, 5.39414227, 0.33212392, -1.2156297], "name": "C2H4O", "molecular_charge": 0.0, "molecular_multiplicity": 1, "fix_com": false, "fix_orientation": false, "provenance": {"creator": "QCElemental", "version": "0.28.0", "routine": "qcelemental.molparse.from_schema"}, "extras": {"notes": {}}}, "39": {"schema_name": "qcschema_molecule", "schema_version": 2, "validated": true, "symbols": ["C", "C", "O", "H", "H", "H", "H"], "geometry": [0.0, 0.0, 0.0, 3.3570579, 0.0, 0.0, -5.0174633, 0.0, -9.0531281, -1.68607595, 0.2404855, 1.73302286, 3.88512886, -0.97653715, 0.91173455, 3.01803679, 2.18919871, 1.39476994, 5.11097622, -0.40106132, -0.71872393], "name": "C2H4O", "molecular_charge": 0.0, "molecular_multiplicity": 1, "fix_com": false, "fix_orientation": false, "provenance": {"creator": "QCElemental", "version": "0.28.0", "routine": "qcelemental.molparse.from_schema"}, "extras": {"notes": {}}}, "40": {"schema_name": "qcschema_molecule", "schema_version": 2, "validated": true, "symbols": ["C", "C", "O", "H", "H", "H", "H"], "geometry": [0.0, 0.0, 0.0, 2.8125631, 0.0, 0.0, -1.74533425, 0.0, -3.24090233, -1.2516145, 0.24894865, 1.74823177, 2.25404975, -1.73962615, 1.83219026, 3.53980913, 0.99186311, 0.42520525, 3.83936256, 0.36695076, -1.90138359], "name": "C2H4O", "molecular_charge": 0.0, "molecular_multiplicity": 1, "fix_com": false, "fix_orientation": false, "provenance": {"creator": "QCElemental", "version": "0.28.0", "routine": "qcelemental.molparse.from_schema"}, "extras": {"notes": {}}}, "41": {"schema_name": "qcschema_molecule", "schema_version": 2, "validated": true, "symbols": ["C", "C", "O", "H", "H", "H", "H"], "geometry": [0.0, 0.0, 0.0, 4.01272355, 0.0, 0.0, -1.82326588, 0.0, -2.23508647, -0.6968149, -0.48204106, 1.96024201, 4.11308693, -2.11215372, 0.70059164, 3.9608976, 1.84181674, 0.72420007, 5.33903111, -0.39260191, -1.42930372], "name": "C2H4O", "molecular_charge": 0.0, "molecular_multiplicity": 1, "fix_com": false, "fix_orientation": false, "provenance": {"creator": "QCElemental", "version": "0.28.0", "routine": "qcelemental.molparse.from_schema"}, "extras": {"notes": {}}}, "42": {"schema_name": "qcschema_molecule", "schema_version": 2, "validated": true, "symbols": ["C", "C", "O", "H", "H", "H", "H"], "geometry": [0.0, 0.0, 0.0, 2.24398413, 0.0, 0.0, -1.73429086, 0.0, -1.09334893, -0.46629827, 0.67860421, 1.51406763, 3.97293136, -3.22591554, 2.25447428, 2.31609224, 1.4870249, -0.31674719, 2.95301024, -0.35405091, -1.53371692], "name": "C2H4O", "molecular_charge": 0.0, "molecular_multiplicity": 1, "fix_com": false, "fix_orientation": false, "provenance": {"creator": "QCElemental", "version": "0.28.0", "routine": "qcelemental.molparse.from_schema"}, "extras": {"notes": {}}}, "43": {"schema_name": "qcschema_molecule", "schema_version": 2, "validated": true, "symbols": ["C", "C", "O", "H", "H", "H", "H"], "geometry": [0.0, 0.0, 0.0, 8.18882738, 0.0, 0.0, -1.20285017, 0.0, -2.35911581, -1.65888213, 0.68690907, 1.29858887, 9.54603173, 0.16668719, 1.56488673, 7.63464782, 2.30369094, 0.13869253, 8.94092216, -1.52636257, -1.20434512], "name": "C2H4O", "molecular_charge": 0.0, "molecular_multiplicity": 1, "fix_com": false, "fix_orientation": false, "provenance": {"creator": "QCElemental", "version": "0.28.0", "routine": "qcelemental.molparse.from_schema"}, "extras": {"notes": {}}}, "44": {"schema_name": "qcschema_molecule", "schema_version": 2, "validated": true, "symbols": ["C", "C", "O", "H", "H", "H", "H"], "geometry": [0.0, 0.0, 0.0, 3.06370486, 0.0, 0.0, -1.11805717, 0.0, -2.24018705, -0.40248043, 0.5773411, 1.23643262, 6.06079836, -5.14592292, 4.47131104, 4.6374338, 1.21674823, 0.30174494, 4.16868464, -0.98633602, -1.67323878], "name": "C2H4O", "molecular_charge": 0.0, "molecular_multiplicity": 1, "fix_com": false, "fix_orientation": false, "provenance": {"creator": "QCElemental", "version": "0.28.0", "routine": "qcelemental.molparse.from_schema"}, "extras": {"notes": {}}}, "45": {"schema_name": "qcschema_molecule", "schema_version": 2, "validated": true, "symbols": ["C", "C", "O", "H", "H", "H", "H"], "geometry": [0.0, 0.0, 0.0, 3.40023135, 0.0, 0.0, -0.97661097, 0.0, -2.04255257, -0.40416862, -0.79856908, 1.99696895, 3.86509211, -1.61171019, 0.01337104, 4.28992107, 0.65186205, 1.70953945, 3.33127106, 0.59392677, -2.10419625], "name": "C2H4O", "molecular_charge": 0.0, "molecular_multiplicity": 1, "fix_com": false, "fix_orientation": false, "provenance": {"creator": "QCElemental", "version": "0.28.0", "routine": "qcelemental.molparse.from_schema"}, "extras": {"notes": {}}}, "46": {"schema_name": "qcschema_molecule", "schema_version": 2, "validated": true, "symbols": ["C", "C", "O", "H", "H", "H", "H"], "geometry": [0.0, 0.0, 0.0, 9.97133098, 0.0, 0.0, -1.4849788, 0.0, -1.79191493, 0.25124673, -1.33386674, 1.75077491, 9.86367347, -1.75322828, -0.96676674, 11.9914184, 0.76125057, 0.80337443, 10.19801786, 1.71728421, -0.85315131], "name": "C2H4O", "molecular_charge": 0.0, "molecular_multiplicity": 1, "fix_com": false, "fix_orientation": false, "provenance": {"creator": "QCElemental", "version": "0.28.0", "routine": "qcelemental.molparse.from_schema"}, "extras": {"notes": {}}}, "47": {"schema_name": "qcschema_molecule", "schema_version": 2, "validated": true, "symbols": ["C", "C", "O", "H", "H", "H", "H"], "geometry": [0.0, 0.0, 0.0, 5.49638523, 0.0, 0.0, -0.74477761, 0.0, -1.7224337, -1.04362772, -0.78794322, 0.94612507, 5.15266924, -2.33877213, 0.20720727, 6.01902548, 1.51200495, 1.15341952, 5.44490221, 1.79275394, -0.8831197], "name": "C2H4O", "molecular_charge": 0.0, "molecular_multiplicity": 1, "fix_com": false, "fix_orientation": false, "provenance": {"creator": "QCElemental", "version": "0.28.0", "routine": "qcelemental.molparse.from_schema"}, "extras": {"notes": {}}}, "48": {"schema_name": "qcschema_molecule", "schema_version": 2, "validated": true, "symbols": ["C", "C", "O", "H", "H", "H", "H"], "geometry": [0.0, 0.0, 0.0, 2.7267106, 0.0, 0.0, -2.41622972, 0.0, -2.1438112, -0.15064668, -0.10465913, 1.90917769, 3.49338469, -2.03934927, 2.37609636, 3.54541088, 1.30543887, 0.53339532, 4.07635096, -0.10803217, -1.75649192], "name": "C2H4O", "molecular_charge": 0.0, "molecular_multiplicity": 1, "fix_com": false, "fix_orientation": false, "provenance": {"creator": "QCElemental", "version": "0.28.0", "routine": "qcelemental.molparse.from_schema"}, "extras": {"notes": {}}}, "49": {"schema_name": "qcschema_molecule", "schema_version": 2, "validated": true, "symbols": ["C", "C", "O", "H", "H", "H", "H"], "geometry": [0.0, 0.0, 0.0, 3.5636329, 0.0, 0.0, -1.08584418, 0.0, -1.46584271, -0.23182935, -1.64903511, 3.6554941, 4.81522774, -2.49001918, 1.44249063, 4.42318362, 1.58209508, 1.51596851, 3.79474133, 0.17572432, -1.32871966], "name": "C2H4O", "molecular_charge": 0.0, "molecular_multiplicity": 1, "fix_com": false, "fix_orientation": false, "provenance": {"creator": "QCElemental", "version": "0.28.0", "routine": "qcelemental.molparse.from_schema"}, "extras": {"notes": {}}}, "50": {"schema_name": "qcschema_molecule", "schema_version": 2, "validated": true, "symbols": ["C", "C", "O", "H", "H", "H", "H"], "geometry": [0.0, 0.0, 0.0, 2.84710472, 0.0, 0.0, -1.77120232, 0.0, -1.41344286, -7.8782135, 5.34072796, 11.09957123, 3.18349381, -0.79591685, 1.74450237, 4.55973445, 1.28546133, 0.39546802, 2.89742563, -0.6939202, -1.81236341], "name": "C2H4O", "molecular_charge": 0.0, "molecular_multiplicity": 1, "fix_com": false, "fix_orientation": false, "provenance": {"creator": "QCElemental", "version": "0.28.0", "routine": "qcelemental.molparse.from_schema"}, "extras": {"notes": {}}}, "51": {"schema_name": "qcschema_molecule", "schema_version": 2, "validated": true, "symbols": ["C", "C", "O", "H", "H", "H", "H"], "geometry": [0.0, 0.0, 0.0, 2.57584468, 0.0, 0.0, -1.47086245, 0.0, -1.87286901, -1.07758518, -4.91883196, 9.04860299, 4.41321268, -0.47733125, -0.19372785, 3.46758573, 0.70165473, 1.25001038, 2.60942626, 0.61242006, -1.53703812], "name": "C2H4O", "molecular_charge": 0.0, "molecular_multiplicity": 1, "fix_com": false, "fix_orientation": false, "provenance": {"creator": "QCElemental", "version": "0.28.0", "routine": "qcelemental.molparse.from_schema"}, "extras": {"notes": {}}}, "52": {"schema_name": "qcschema_molecule", "schema_version": 2, "validated": true, "symbols": ["C", "C", "O", "H", "H", "H", "H"], "geometry": [0.0, 0.0, 0.0, 2.91668668, 0.0, 0.0, -1.69402794, 0.0, -1.53073721, -1.49658001, 0.45697299, 2.99117667, 4.03499107, -1.64510671, 1.09194287, 2.50168132, 3.04621838, 0.46847617, 4.95444602, -0.73303256, -1.44319885], "name": "C2H4O", "molecular_charge": 0.0, "molecular_multiplicity": 1, "fix_com": false, "fix_orientation": false, "provenance": {"creator": "QCElemental", "version": "0.28.0", "routine": "qcelemental.molparse.from_schema"}, "extras": {"notes": {}}}, "53": {"schema_name": "qcschema_molecule", "schema_version": 2, "validated": true, "symbols": ["C", "C", "O", "H", "H", "H", "H"], "geometry": [0.0, 0.0, 0.0, 4.16380765, 0.0, 0.0, -1.61392814, 0.0, -3.05148876, -1.04468357, 0.76594646, 1.26725405, 3.96542725, -1.45906587, 1.203006, 6.43632061, 1.18473039, 0.42521833, 6.42176693, -1.72975627, -1.0733978], "name": "C2H4O", "molecular_charge": 0.0, "molecular_multiplicity": 1, "fix_com": false, "fix_orientation": false, "provenance": {"creator": "QCElemental", "version": "0.28.0", "routine": "qcelemental.molparse.from_schema"}, "extras": {"notes": {}}}, "54": {"schema_name": "qcschema_molecule", "schema_version": 2, "validated": true, "symbols": ["C", "C", "O", "H", "H", "H", "H"], "geometry": [0.0, 0.0, 0.0, 2.41704894, 0.0, 0.0, -0.53480872, 0.0, -1.89582062, -2.01488688, 0.19226289, 1.00281848, 8.19244153, -1.3141369, 2.45419909, 3.2174225, 0.98888109, 0.31820449, 2.45406407, -0.0487187, -1.90467161], "name": "C2H4O", "molecular_charge": 0.0, "molecular_multiplicity": 1, "fix_com": false, "fix_orientation": false, "provenance": {"creator": "QCElemental", "version": "0.28.0", "routine": "qcelemental.molparse.from_schema"}, "extras": {"notes": {}}}, "55": {"schema_name": "qcschema_molecule", "schema_version": 2, "validated": true, "symbols": ["C", "C", "O", "H", "H", "H", "H"], "geometry": [0.0, 0.0, 0.0, 4.20376015, 0.0, 0.0, -0.74243245, 0.0, -1.51904132, -0.51429935, -0.00074469, 1.40906258, 3.78325651, -1.13803469, 0.95645763, 5.31275663, 2.3321219, 1.92277739, 4.67954626, 0.22665428, -2.31902107], "name": "C2H4O", "molecular_charge": 0.0, "molecular_multiplicity": 1, "fix_com": false, "fix_orientation": false, "provenance": {"creator": "QCElemental", "version": "0.28.0", "routine": "qcelemental.molparse.from_schema"}, "extras": {"notes": {}}}, "56": {"schema_name": "qcschema_molecule", "schema_version": 2, "validated": true, "symbols": ["C", "C", "O", "H", "H", "H", "H"], "geometry": [0.0, 0.0, 0.0, 2.23109683, 0.0, 0.0, -1.39770826, 0.0, -1.53467951, -1.04961141, -0.72228686, 1.37336886, 2.86580586, -1.6282942, -0.56214599, 2.91877991, 0.40233654, 1.77366801, 2.8145739, 0.61316124, -1.70303437], "name": "C2H4O", "molecular_charge": 0.0, "molecular_multiplicity": 1, "fix_com": false, "fix_orientation": false, "provenance": {"creator": "QCElemental", "version": "0.28.0", "routine": "qcelemental.molparse.from_schema"}, "extras": {"notes": {}}}, "57": {"schema_name": "qcschema_molecule", "schema_version": 2, "validated": true, "symbols": ["C", "C", "O", "H", "H", "H", "H"], "geometry": [0.0, 0.0, 0.0, 3.32265236, 0.0, 0.0, -2.91050627, 0.0, -0.43900158, -0.53195041, 0.6575412, 2.40206283, 3.70120685, -1.93020632, 0.47507272, 4.14705515, 1.92899616, -0.55876772, 2.52278556, -0.99111997, -0.95558144], "name": "C2H4O", "molecular_charge": 0.0, "molecular_multiplicity": 1, "fix_com": false, "fix_orientation": false, "provenance": {"creator": "QCElemental", "version": "0.28.0", "routine": "qcelemental.molparse.from_schema"}, "extras": {"notes": {}}}, "58": {"schema_name": "qcschema_molecule", "schema_version": 2, "validated": true, "symbols": ["C", "C", "O", "H", "H", "H", "H"], "geometry": [0.0, 0.0, 0.0, 2.59671987, 0.0, 0.0, -0.78923892, 0.0, -2.34743795, -0.13537163, -0.459653, 2.92529979, 2.59942879, -2.27659321, 0.5896462, 3.54262694, 0.64180376, 0.87804267, 2.38090563, 0.30859965, -1.28102394], "name": "C2H4O", "molecular_charge": 0.0, "molecular_multiplicity": 1, "fix_com": false, "fix_orientation": false, "provenance": {"creator": "QCElemental", "version": "0.28.0", "routine": "qcelemental.molparse.from_schema"}, "extras": {"notes": {}}}, "59": {"schema_name": "qcschema_molecule", "schema_version": 2, "validated": true, "symbols": ["C", "C", "O", "H", "H", "H", "H"], "geometry": [0.0, 0.0, 0.0, 3.24638611, 0.0, 0.0, -1.97806121, 0.0, -0.69430506, -0.11492845, -0.92329259, 1.59904443, 3.68207524, -4.51748296, -2.13004173, 3.8470356, 0.919609, 1.83618929, 4.1510297, 0.02549731, -1.55211408], "name": "C2H4O", "molecular_charge": 0.0, "molecular_multiplicity": 1, "fix_com": false, "fix_orientation": false, "provenance": {"creator": "QCElemental", "version": "0.28.0", "routine": "qcelemental.molparse.from_schema"}, "extras": {"notes": {}}}, "60": {"schema_name": "qcschema_molecule", "schema_version": 2, "validated": true, "symbols": ["C", "C", "O", "H", "H", "H", "H"], "geometry": [0.0, 0.0, 0.0, 2.68525654, 0.0, 0.0, -7.0598748, 0.0, -5.25839109, -1.26977542, -0.50374838, 2.36696971, 1.83620254, -0.66339183, 1.061581, 3.23056668, 1.21839798, 2.5735154, 3.39495086, -1.04395674, -2.35984312], "name": "C2H4O", "molecular_charge": 0.0, "molecular_multiplicity": 1, "fix_com": false, "fix_orientation": false, "provenance": {"creator": "QCElemental", "version": "0.28.0", "routine": "qcelemental.molparse.from_schema"}, "extras": {"notes": {}}}, "61": {"schema_name": "qcschema_molecule", "schema_version": 2, "validated": true, "symbols": ["C", "C", "O", "H", "H", "H", "H"], "geometry": [0.0, 0.0, 0.0, 2.73192242, 0.0, 0.0, -4.8276622, 0.0, -8.48715724, -0.68556436, 0.55390452, 1.39487595, 4.18610146, -0.27541229, 1.90250019, 2.90457362, 1.29191003, 0.43061294, 3.86451585, -0.37445605, -1.51395468], "name": "C2H4O", "molecular_charge": 0.0, "molecular_multiplicity": 1, "fix_com": false, "fix_orientation": false, "provenance": {"creator": "QCElemental", "version": "0.28.0", "routine": "qcelemental.molparse.from_schema"}, "extras": {"notes": {}}}, "62": {"schema_name": "qcschema_molecule", "schema_version": 2, "validated": true, "symbols": ["C", "C", "O", "H", "H", "H", "H"], "geometry": [0.0, 0.0, 0.0, 2.26787985, 0.0, 0.0, -1.18827544, 0.0, -1.82463265, -6.324272, 1.53195241, 10.73714793, 3.01997814, -1.96340622, 1.09499544, 3.41836578, 0.68223094, 0.20700938, 2.42482614, -0.86064479, -1.42664989], "name": "C2H4O", "molecular_charge": 0.0, "molecular_multiplicity": 1, "fix_com": false, "fix_orientation": false, "provenance": {"creator": "QCElemental", "version": "0.28.0", "routine": "qcelemental.molparse.from_schema"}, "extras": {"notes": {}}}, "63": {"schema_name": "qcschema_molecule", "schema_version": 2, "validated": true, "symbols": ["C", "C", "O", "H", "H", "H", "H"], "geometry": [0.0, 0.0, 0.0, 3.21162691, 0.0, 0.0, -1.10763339, 0.0, -2.71459073, -0.80063422, 0.39634145, 2.44681812, 3.71529819, -1.13922685, 2.10557468, 4.6703392, 1.2159012, 0.5820975, 3.3569203, -2.393375, -2.07254046], "name": "C2H4O", "molecular_charge": 0.0, "molecular_multiplicity": 1, "fix_com": false, "fix_orientation": false, "provenance": {"creator": "QCElemental", "version": "0.28.0", "routine": "qcelemental.molparse.from_schema"}, "extras": {"notes": {}}}, "64": {"schema_name": "qcschema_molecule", "schema_version": 2, "validated": true, "symbols": ["C", "C", "O", "H", "H", "H", "H"], "geometry": [0.0, 0.0, 0.0, 3.1730357, 0.0, 0.0, -1.38267315, 0.0, -4.2198139, -2.10062888, 0.45673123, 1.11290591, 4.27851565, 0.04811622, 1.19357115, 2.73831996, 2.51553395, 0.42257255, 3.734817, -1.27762115, -0.56326785], "name": "C2H4O", "molecular_charge": 0.0, "molecular_multiplicity": 1, "fix_com": false, "fix_orientation": false, "provenance": {"creator": "QCElemental", "version": "0.28.0", "routine": "qcelemental.molparse.from_schema"}, "extras": {"notes": {}}}, "65": {"schema_name": "qcschema_molecule", "schema_version": 2, "validated": true, "symbols": ["C", "C", "O", "H", "H", "H", "H"], "geometry": [0.0, 0.0, 0.0, 1.81843633, 0.0, 0.0, 1.16327862, 0.0, -2.29476524, -1.88874554, -0.85800754, 1.11914665, 1.7929522, -3.55051454, 1.00270325, 3.32589922, 1.13224796, 1.1682596, 2.43019082, 0.78597485, -1.46961618], "name": "C2H4O", "molecular_charge": 0.0, "molecular_multiplicity": 1, "fix_com": false, "fix_orientation": false, "provenance": {"creator": "QCElemental", "version": "0.28.0", "routine": "qcelemental.molparse.from_schema"}, "extras": {"notes": {}}}, "66": {"schema_name": "qcschema_molecule", "schema_version": 2, "validated": true, "symbols": ["C", "C", "O", "H", "H", "H", "H"], "geometry": [0.0, 0.0, 0.0, 2.90276507, 0.0, 0.0, -0.5239155, 0.0, -3.9883909, -2.01444315, -0.49102538, 1.20587901, 4.41303128, -0.19223898, -0.03972842, 3.07011937, 0.88052065, 1.4613745, 3.05902733, 0.29656651, -1.82231179], "name": "C2H4O", "molecular_charge": 0.0, "molecular_multiplicity": 1, "fix_com": false, "fix_orientation": false, "provenance": {"creator": "QCElemental", "version": "0.28.0", "routine": "qcelemental.molparse.from_schema"}, "extras": {"notes": {}}}, "67": {"schema_name": "qcschema_molecule", "schema_version": 2, "validated": true, "symbols": ["C", "C", "O", "H", "H", "H", "H"], "geometry": [0.0, 0.0, 0.0, 2.00188162, 0.0, 0.0, -1.70560582, 0.0, -1.12676345, -1.73836536, 0.47776963, 1.4520638, 5.34115749, -1.85290538, 0.80721631, 2.67959839, 2.26903514, -0.14287872, 2.30041878, -0.74109626, -1.73657252], "name": "C2H4O", "molecular_charge": 0.0, "molecular_multiplicity": 1, "fix_com": false, "fix_orientation": false, "provenance": {"creator": "QCElemental", "version": "0.28.0", "routine": "qcelemental.molparse.from_schema"}, "extras": {"notes": {}}}, "68": {"schema_name": "qcschema_molecule", "schema_version": 2, "validated": true, "symbols": ["C", "C", "O", "H", "H", "H", "H"], "geometry": [0.0, 0.0, 0.0, 4.66274468, 0.0, 0.0, -1.61806661, 0.0, -0.85831471, -1.30576864, 1.58211309, 1.61285047, 2.82905533, -0.28091396, 5.40300612, 6.52165663, 2.21594863, 1.2858713, 5.34489551, -1.1666679, -1.27787144], "name": "C2H4O", "molecular_charge": 0.0, "molecular_multiplicity": 1, "fix_com": false, "fix_orientation": false, "provenance": {"creator": "QCElemental", "version": "0.28.0", "routine": "qcelemental.molparse.from_schema"}, "extras": {"notes": {}}}, "69": {"schema_name": "qcschema_molecule", "schema_version": 2, "validated": true, "symbols": ["C", "C", "O", "H", "H", "H", "H"], "geometry": [0.0, 0.0, 0.0, 8.91033098, 0.0, 0.0, -1.07901976, 0.0, -2.02160362, -1.41634043, -0.65726443, 2.06126396, 10.08431169, -1.32303717, 0.60984411, 9.01113929, 1.02923192, 0.89351225, 9.50658005, 0.24419146, -1.95667384], "name": "C2H4O", "molecular_charge": 0.0, "molecular_multiplicity": 1, "fix_com": false, "fix_orientation": false, "provenance": {"creator": "QCElemental", "version": "0.28.0", "routine": "qcelemental.molparse.from_schema"}, "extras": {"notes": {}}}, "70": {"schema_name": "qcschema_molecule", "schema_version": 2, "validated": true, "symbols": ["C", "C", "O", "H", "H", "H", "H"], "geometry": [0.0, 0.0, 0.0, 3.66479179, 0.0, 0.0, -1.79263222, 0.0, -0.84274004, -1.23403351, -0.08332844, 10.25860627, 3.68108151, -0.83029831, 1.44891307, 4.03871798, 1.40144141, 0.86574703, 4.13524441, 0.86252124, -2.07099749], "name": "C2H4O", "molecular_charge": 0.0, "molecular_multiplicity": 1, "fix_com": false, "fix_orientation": false, "provenance": {"creator": "QCElemental", "version": "0.28.0", "routine": "qcelemental.molparse.from_schema"}, "extras": {"notes": {}}}, "71": {"schema_name": "qcschema_molecule", "schema_version": 2, "validated": true, "symbols": ["C", "C", "O", "H", "H", "H", "H"], "geometry": [0.0, 0.0, 0.0, 11.13993047, 0.0, 0.0, -0.32731934, 0.0, -1.56617697, 1.11773319, -1.14763911, 2.9785136, 12.8568198, -2.09448956, 0.11652723, 12.99512985, 1.55188216, 0.04220815, 11.21418048, 0.14468036, -1.57741557], "name": "C2H4O", "molecular_charge": 0.0, "molecular_multiplicity": 1, "fix_com": false, "fix_orientation": false, "provenance": {"creator": "QCElemental", "version": "0.28.0", "routine": "qcelemental.molparse.from_schema"}, "extras": {"notes": {}}}, "72": {"schema_name": "qcschema_molecule", "schema_version": 2, "validated": true, "symbols": ["C", "C", "O", "H", "H", "H", "H"], "geometry": [0.0, 0.0, 0.0, 11.20970235, 0.0, 0.0, -0.49379306, 0.0, -1.44269783, -0.83704192, 1.64375204, 2.39453579, 10.32466827, -0.96175069, 1.35073292, 12.417993, 1.40832897, -0.41326748, 11.97524943, -1.9528222, -0.09084391], "name": "C2H4O", "molecular_charge": 0.0, "molecular_multiplicity": 1, "fix_com": false, "fix_orientation": false, "provenance": {"creator": "QCElemental", "version": "0.28.0", "routine": "qcelemental.molparse.from_schema"}, "extras": {"notes": {}}}, "73": {"schema_name": "qcschema_molecule", "schema_version": 2, "validated": true, "symbols": ["C", "C", "O", "H", "H", "H", "H"], "geometry": [0.0, 0.0, 0.0, 4.04450829, 0.0, 0.0, 0.36411749, 0.0, -2.02754677, -1.14786822, -1.16207422, 1.32883161, 5.51385566, -2.03774322, -0.11786219, 5.36441693, 0.77035878, 1.86339729, 5.57749615, 0.51176286, -0.29939892], "name": "C2H4O", "molecular_charge": 0.0, "molecular_multiplicity": 1, "fix_com": false, "fix_orientation": false, "provenance": {"creator": "QCElemental", "version": "0.28.0", "routine": "qcelemental.molparse.from_schema"}, "extras": {"notes": {}}}, "74": {"schema_name": "qcschema_molecule", "schema_version": 2, "validated": true, "symbols": ["C", "C", "O", "H", "H", "H", "H"], "geometry": [0.0, 0.0, 0.0, 2.85265397, 0.0, 0.0, -1.80373197, 0.0, -1.74807815, -0.74180556, 0.8413234, 1.4669577, 5.41504867, -2.01752771, 2.93245707, 3.20321946, 1.90552127, 0.04262836, 3.21492297, -1.7387157, -1.79462897], "name": "C2H4O", "molecular_charge": 0.0, "molecular_multiplicity": 1, "fix_com": false, "fix_orientation": false, "provenance": {"creator": "QCElemental", "version": "0.28.0", "routine": "qcelemental.molparse.from_schema"}, "extras": {"notes": {}}}, "75": {"schema_name": "qcschema_molecule", "schema_version": 2, "validated": true, "symbols": ["C", "C", "O", "H", "H", "H", "H"], "geometry": [0.0, 0.0, 0.0, 2.7550683, 0.0, 0.0, -1.74195037, 0.0, -0.98994557, -0.63772867, -0.62591522, 2.04822336, 3.68386528, -1.34602933, 0.66929414, 3.76208441, 2.08314728, 1.60847277, 3.65966344, 0.20550706, -1.07668082], "name": "C2H4O", "molecular_charge": 0.0, "molecular_multiplicity": 1, "fix_com": false, "fix_orientation": false, "provenance": {"creator": "QCElemental", "version": "0.28.0", "routine": "qcelemental.molparse.from_schema"}, "extras": {"notes": {}}}, "76": {"schema_name": "qcschema_molecule", "schema_version": 2, "validated": true, "symbols": ["C", "C", "O", "H", "H", "H", "H"], "geometry": [0.0, 0.0, 0.0, 3.33619188, 0.0, 0.0, -3.95244119, 0.0, -3.03803879, -1.04049439, -0.16190941, 1.53928295, 3.15967729, -1.87025288, 0.70543156, 4.52316292, 0.98521931, 1.54842085, 5.20412452, 0.24358011, -1.76159658], "name": "C2H4O", "molecular_charge": 0.0, "molecular_multiplicity": 1, "fix_com": false, "fix_orientation": false, "provenance": {"creator": "QCElemental", "version": "0.28.0", "routine": "qcelemental.molparse.from_schema"}, "extras": {"notes": {}}}, "77": {"schema_name": "qcschema_molecule", "schema_version": 2, "validated": true, "symbols": ["C", "C", "O", "H", "H", "H", "H"], "geometry": [0.0, 0.0, 0.0, 2.47247215, 0.0, 0.0, -2.06152772, 0.0, -1.2151867, -1.13657321, 1.27968229, 1.05941721, 3.12617345, -3.05207188, 3.34618131, 2.42303579, 1.35092131, -1.31484374, 2.81073015, -1.86011025, -0.45788522], "name": "C2H4O", "molecular_charge": 0.0, "molecular_multiplicity": 1, "fix_com": false, "fix_orientation": false, "provenance": {"creator": "QCElemental", "version": "0.28.0", "routine": "qcelemental.molparse.from_schema"}, "extras": {"notes": {}}}, "78": {"schema_name": "qcschema_molecule", "schema_version": 2, "validated": true, "symbols": ["C", "C", "O", "H", "H", "H", "H"], "geometry": [0.0, 0.0, 0.0, 3.93654872, 0.0, 0.0, -0.51567934, 0.0, -3.18721368, -0.56573499, -0.15716738, 2.09978119, 4.51723091, -1.53672834, 0.74804423, 5.00566418, 1.87085088, -0.82198071, 5.52860506, -0.20072229, -0.80912644], "name": "C2H4O", "molecular_charge": 0.0, "molecular_multiplicity": 1, "fix_com": false, "fix_orientation": false, "provenance": {"creator": "QCElemental", "version": "0.28.0", "routine": "qcelemental.molparse.from_schema"}, "extras": {"notes": {}}}, "79": {"schema_name": "qcschema_molecule", "schema_version": 2, "validated": true, "symbols": ["C", "C", "O", "H", "H", "H", "H"], "geometry": [0.0, 0.0, 0.0, 2.83240705, 0.0, 0.0, 1.29361185, 0.0, -7.12693864, -1.06337418, -0.04351296, 1.47413614, 2.25711148, -1.18084961, 1.19853226, 3.85026498, 1.83135579, 1.0152443, 4.04597894, 0.35863436, -2.19787478], "name": "C2H4O", "molecular_charge": 0.0, "molecular_multiplicity": 1, "fix_com": false, "fix_orientation": false, "provenance": {"creator": "QCElemental", "version": "0.28.0", "routine": "qcelemental.molparse.from_schema"}, "extras": {"notes": {}}}, "80": {"schema_name": "qcschema_molecule", "schema_version": 2, "validated": true, "symbols": ["C", "C", "O", "H", "H", "H", "H"], "geometry": [0.0, 0.0, 0.0, 3.55640688, 0.0, 0.0, -0.58104016, 0.0, -2.02646202, -0.07415244, -0.9068817, 1.91373376, 3.96616539, -1.94889126, -0.9113757, 5.91397225, 0.86091541, 0.6906252, 3.32504338, 0.05623111, -2.3221408], "name": "C2H4O", "molecular_charge": 0.0, "molecular_multiplicity": 1, "fix_com": false, "fix_orientation": false, "provenance": {"creator": "QCElemental", "version": "0.28.0", "routine": "qcelemental.molparse.from_schema"}, "extras": {"notes": {}}}, "81": {"schema_name": "qcschema_molecule", "schema_version": 2, "validated": true, "symbols": ["C", "C", "O", "H", "H", "H", "H"], "geometry": [0.0, 0.0, 0.0, 2.2850421, 0.0, 0.0, -1.63129139, 0.0, -6.45502592, -0.24076775, -0.15899153, 2.41796043, 2.31468403, -1.70747839, -0.57151474, 2.98709633, 1.37564738, 0.68801373, 3.43461879, 0.42182688, -0.58141651], "name": "C2H4O", "molecular_charge": 0.0, "molecular_multiplicity": 1, "fix_com": false, "fix_orientation": false, "provenance": {"creator": "QCElemental", "version": "0.28.0", "routine": "qcelemental.molparse.from_schema"}, "extras": {"notes": {}}}, "82": {"schema_name": "qcschema_molecule", "schema_version": 2, "validated": true, "symbols": ["C", "C", "O", "H", "H", "H", "H"], "geometry": [0.0, 0.0, 0.0, 3.06198249, 0.0, 0.0, -1.30393422, 0.0, -1.28462148, -4.13610518, -8.37882274, 5.88456918, 3.85200071, -1.21630073, -0.72503308, 3.56371384, -0.12287901, 1.3653975, 3.07091784, 1.27284108, -1.6241064], "name": "C2H4O", "molecular_charge": 0.0, "molecular_multiplicity": 1, "fix_com": false, "fix_orientation": false, "provenance": {"creator": "QCElemental", "version": "0.28.0", "routine": "qcelemental.molparse.from_schema"}, "extras": {"notes": {}}}, "83": {"schema_name": "qcschema_molecule", "schema_version": 2, "validated": true, "symbols": ["C", "C", "O", "H", "H", "H", "H"], "geometry": [0.0, 0.0, 0.0, 1.80293448, 0.0, 0.0, -1.70448543, 0.0, -1.30568412, 0.29667609, 1.33545037, 3.26967848, 1.43026894, -1.57466553, 2.1753228, 1.81853861, 1.79116841, 0.43128179, 2.98628461, -0.81540938, -1.37346237], "name": "C2H4O", "molecular_charge": 0.0, "molecular_multiplicity": 1, "fix_com": false, "fix_orientation": false, "provenance": {"creator": "QCElemental", "version": "0.28.0", "routine": "qcelemental.molparse.from_schema"}, "extras": {"notes": {}}}, "84": {"schema_name": "qcschema_molecule", "schema_version": 2, "validated": true, "symbols": ["C", "C", "O", "H", "H", "H", "H"], "geometry": [0.0, 0.0, 0.0, 3.13305839, 0.0, 0.0, -1.77192954, 0.0, -1.67923122, -0.48513272, 0.45613344, 5.30276975, 3.22898195, -1.48520915, 1.60046837, 3.56210494, 1.51033633, -0.57457368, 3.5469925, 0.06115386, -1.53393922], "name": "C2H4O", "molecular_charge": 0.0, "molecular_multiplicity": 1, "fix_com": false, "fix_orientation": false, "provenance": {"creator": "QCElemental", "version": "0.28.0", "routine": "qcelemental.molparse.from_schema"}, "extras": {"notes": {}}}, "85": {"schema_name": "qcschema_molecule", "schema_version": 2, "validated": true, "symbols": ["C", "C", "O", "H", "H", "H", "H"], "geometry": [0.0, 0.0, 0.0, 2.09781298, 0.0, 0.0, -2.71980234, 0.0, -1.26980788, -3.05802358, -0.02946372, 4.35607234, 1.67344579, -1.01687174, 1.90616489, 4.47298464, 1.794349, 1.46532908, 2.77704856, -0.48260868, -1.67712266], "name": "C2H4O", "molecular_charge": 0.0, "molecular_multiplicity": 1, "fix_com": false, "fix_orientation": false, "provenance": {"creator": "QCElemental", "version": "0.28.0", "routine": "qcelemental.molparse.from_schema"}, "extras": {"notes": {}}}, "86": {"schema_name": "qcschema_molecule", "schema_version": 2, "validated": true, "symbols": ["C", "C", "O", "H", "H", "H", "H"], "geometry": [0.0, 0.0, 0.0, 1.83328374, 0.0, 0.0, -1.45454991, 0.0, -1.82544518, -0.57652816, 1.0647834, 1.4037599, 4.91197093, -4.23222365, 2.40153221, 1.63312056, 1.35050426, 0.157999, 2.86377793, 0.25589143, -0.90771131], "name": "C2H4O", "molecular_charge": 0.0, "molecular_multiplicity": 1, "fix_com": false, "fix_orientation": false, "provenance": {"creator": "QCElemental", "version": "0.28.0", "routine": "qcelemental.molparse.from_schema"}, "extras": {"notes": {}}}, "87": {"schema_name": "qcschema_molecule", "schema_version": 2, "validated": true, "symbols": ["C", "C", "O", "H", "H", "H", "H"], "geometry": [0.0, 0.0, 0.0, 2.97858185, 0.0, 0.0, -1.04858827, 0.0, -1.36976669, -2.78113761, 17.47989202, 11.87081369, 5.2877872, -0.54115987, 0.52503367, 4.18952976, 1.49664867, -1.0911051, 3.42403466, -1.57731763, -0.10112944], "name": "C2H4O", "molecular_charge": 0.0, "molecular_multiplicity": 1, "fix_com": false, "fix_orientation": false, "provenance": {"creator": "QCElemental", "version": "0.28.0", "routine": "qcelemental.molparse.from_schema"}, "extras": {"notes": {}}}, "88": {"schema_name": "qcschema_molecule", "schema_version": 2, "validated": true, "symbols": ["C", "C", "O", "H", "H", "H", "H"], "geometry": [0.0, 0.0, 0.0, 3.64233597, 0.0, 0.0, -6.47801472, 0.0, -9.27233063, -0.12979297, 0.35993284, 1.95231336, 3.88370912, -0.18185413, 1.79744147, 4.5721268, 1.2144491, -0.29337558, 4.70804876, -0.85569334, -2.18714917], "name": "C2H4O", "molecular_charge": 0.0, "molecular_multiplicity": 1, "fix_com": false, "fix_orientation": false, "provenance": {"creator": "QCElemental", "version": "0.28.0", "routine": "qcelemental.molparse.from_schema"}, "extras": {"notes": {}}}, "89": {"schema_name": "qcschema_molecule", "schema_version": 2, "validated": true, "symbols": ["C", "C", "O", "H", "H", "H", "H"], "geometry": [0.0, 0.0, 0.0, 3.77162352, 0.0, 0.0, 1.02511448, 0.0, -6.94488294, 0.5678442, 0.4361074, 2.46795743, 5.3302798, -0.77334974, 0.67379447, 4.17237621, 1.99093955, 1.20209859, 4.10877985, 0.68621443, -1.27458892], "name": "C2H4O", "molecular_charge": 0.0, "molecular_multiplicity": 1, "fix_com": false, "fix_orientation": false, "provenance": {"creator": "QCElemental", "version": "0.28.0", "routine": "qcelemental.molparse.from_schema"}, "extras": {"notes": {}}}, "90": {"schema_name": "qcschema_molecule", "schema_version": 2, "validated": true, "symbols": ["C", "C", "O", "H", "H", "H", "H"], "geometry": [0.0, 0.0, 0.0, 1.99479208, 0.0, 0.0, -1.11331635, 0.0, -2.56265872, -0.38890317, 0.44078372, 3.11181364, 1.69579571, -2.37401498, 0.51417144, 2.07305019, 1.22022873, 0.68964743, 2.24639558, 1.23259867, -2.04772835], "name": "C2H4O", "molecular_charge": 0.0, "molecular_multiplicity": 1, "fix_com": false, "fix_orientation": false, "provenance": {"creator": "QCElemental", "version": "0.28.0", "routine": "qcelemental.molparse.from_schema"}, "extras": {"notes": {}}}, "91": {"schema_name": "qcschema_molecule", "schema_version": 2, "validated": true, "symbols": ["C", "C", "O", "H", "H", "H", "H"], "geometry": [0.0, 0.0, 0.0, 3.83960022, 0.0, 0.0, -1.76576218, 0.0, -1.12827971, -0.401775, 3.21863213, 5.25824473, 3.71610953, -1.59051466, 0.5155588, 4.60601393, 2.09082138, -0.39783083, 5.48523242, -0.6230491, -0.2785283], "name": "C2H4O", "molecular_charge": 0.0, "molecular_multiplicity": 1, "fix_com": false, "fix_orientation": false, "provenance": {"creator": "QCElemental", "version": "0.28.0", "routine": "qcelemental.molparse.from_schema"}, "extras": {"notes": {}}}, "92": {"schema_name": "qcschema_molecule", "schema_version": 2, "validated": true, "symbols": ["C", "C", "O", "H", "H", "H", "H"], "geometry": [0.0, 0.0, 0.0, 2.95888693, 0.0, 0.0, -2.10847816, 0.0, -1.18321115, 0.69903889, -0.07037261, 2.32863016, 3.50076518, -1.05674565, 0.9071624, 3.16185872, 1.97374212, 0.65112649, 5.22033339, -0.79507229, -1.32019423], "name": "C2H4O", "molecular_charge": 0.0, "molecular_multiplicity": 1, "fix_com": false, "fix_orientation": false, "provenance": {"creator": "QCElemental", "version": "0.28.0", "routine": "qcelemental.molparse.from_schema"}, "extras": {"notes": {}}}, "93": {"schema_name": "qcschema_molecule", "schema_version": 2, "validated": true, "symbols": ["C", "C", "O", "H", "H", "H", "H"], "geometry": [0.0, 0.0, 0.0, 3.18607395, 0.0, 0.0, -2.6571025, 0.0, -7.8588466, -1.81637679, -0.40269473, 0.86523127, 3.50503115, -1.69533098, 0.79275639, 2.48000334, 1.84340364, 1.04304667, 4.97147908, -1.29654306, -1.48028424], "name": "C2H4O", "molecular_charge": 0.0, "molecular_multiplicity": 1, "fix_com": false, "fix_orientation": false, "provenance": {"creator": "QCElemental", "version": "0.28.0", "routine": "qcelemental.molparse.from_schema"}, "extras": {"notes": {}}}, "94": {"schema_name": "qcschema_molecule", "schema_version": 2, "validated": true, "symbols": ["C", "C", "O", "H", "H", "H", "H"], "geometry": [0.0, 0.0, 0.0, 8.03893879, 0.0, 0.0, -0.99283903, 0.0, -1.68574102, -0.86423882, 0.84736756, 1.41673997, 8.88863456, -0.20978336, 1.98247083, 8.79580495, 2.68108316, 0.27670443, 8.26467772, -1.97829729, -1.0161641], "name": "C2H4O", "molecular_charge": 0.0, "molecular_multiplicity": 1, "fix_com": false, "fix_orientation": false, "provenance": {"creator": "QCElemental", "version": "0.28.0", "routine": "qcelemental.molparse.from_schema"}, "extras": {"notes": {}}}, "95": {"schema_name": "qcschema_molecule", "schema_version": 2, "validated": true, "symbols": ["C", "C", "O", "H", "H", "H", "H"], "geometry": [0.0, 0.0, 0.0, 2.37488106, 0.0, 0.0, -1.19697236, 0.0, -1.22806894, -1.90630068, 0.10845769, 0.63326298, 2.84130138, -0.92462629, 1.5730466, 1.83907481, 2.40830878, 1.14234049, 4.58103365, 0.64741654, -1.70153698], "name": "C2H4O", "molecular_charge": 0.0, "molecular_multiplicity": 1, "fix_com": false, "fix_orientation": false, "provenance": {"creator": "QCElemental", "version": "0.28.0", "routine": "qcelemental.molparse.from_schema"}, "extras": {"notes": {}}}, "96": {"schema_name": "qcschema_molecule", "schema_version": 2, "validated": true, "symbols": ["C", "C", "O", "H", "H", "H", "H"], "geometry": [0.0, 0.0, 0.0, 1.99357805, 0.0, 0.0, -2.92631929, 0.0, 0.59176966, -0.97750039, -0.01648444, -0.97334931, 1.82953394, 1.25794944, -0.44465268, 4.05645824, -0.69847102, -1.97388542, 2.39839183, -0.3136148, 3.08053915], "name": "C2H4O", "molecular_charge": 0.0, "molecular_multiplicity": 1, "fix_com": false, "fix_orientation": false, "provenance": {"creator": "QCElemental", "version": "0.28.0", "routine": "qcelemental.molparse.from_schema"}, "extras": {"notes": {}}}, "97": {"schema_name": "qcschema_molecule", "schema_version": 2, "validated": true, "symbols": ["C", "C", "O", "H", "H", "H", "H"], "geometry": [0.0, 0.0, 0.0, 3.35866808, 0.0, 0.0, -14.73635195, 0.0, -7.9567327, -0.9089526, 0.62337209, 1.33298553, 2.79432602, -0.88233578, 1.90247159, 4.78384116, 1.03054439, 0.45720457, 1.8619907, -1.02797562, -1.61337243], "name": "C2H4O", "molecular_charge": 0.0, "molecular_multiplicity": 1, "fix_com": false, "fix_orientation": false, "provenance": {"creator": "QCElemental", "version": "0.28.0", "routine": "qcelemental.molparse.from_schema"}, "extras": {"notes": {}}}, "98": {"schema_name": "qcschema_molecule", "schema_version": 2, "validated": true, "symbols": ["C", "C", "O", "H", "H", "H", "H"], "geometry": [0.0, 0.0, 0.0, 2.36946154, 0.0, 0.0, -0.4456851, 0.0, -3.02794753, -1.2520252, 0.76145827, 1.58928777, 2.11225659, -1.41697842, 2.62220345, 3.29570547, 1.35846233, 1.18433046, 3.90883069, -0.66978521, -1.27341948], "name": "C2H4O", "molecular_charge": 0.0, "molecular_multiplicity": 1, "fix_com": false, "fix_orientation": false, "provenance": {"creator": "QCElemental", "version": "0.28.0", "routine": "qcelemental.molparse.from_schema"}, "extras": {"notes": {}}}, "99": {"schema_name": "qcschema_molecule", "schema_version": 2, "validated": true, "symbols": ["C", "C", "O", "H", "H", "H", "H"], "geometry": [0.0, 0.0, 0.0, 8.64199531, 0.0, 0.0, -2.13382011, 0.0, 0.16212286, -0.84657943, -0.21233856, -2.14888816, 8.45801918, 1.95912828, -1.48716528, 8.69578754, -1.68783317, -0.93178895, 8.50380286, 0.57355072, 1.77638877], "name": "C2H4O", "molecular_charge": 0.0, "molecular_multiplicity": 1, "fix_com": false, "fix_orientation": false, "provenance": {"creator": "QCElemental", "version": "0.28.0", "routine": "qcelemental.molparse.from_schema"}, "extras": {"notes": {}}}}