{"0": {"schema_name": "qcschema_molecule", "schema_version": 2, "validated": true, "symbols": ["B", "H", "H", "H"], "geometry": [0.0, 0.0, 0.0, 8.69205057, 0.0, 0.0, -1.23300037, 0.0, -2.13561928, -0.76780002, 0.0, 1.32986864], "name": "BH3", "molecular_charge": 0.0, "molecular_multiplicity": 1, "fix_com": false, "fix_orientation": false, "provenance": {"creator": "QCElemental", "version": "0.28.0", "routine": "qcelemental.molparse.from_schema"}, "extras": {"notes": {}}}, "1": {"schema_name": "qcschema_molecule", "schema_version": 2, "validated": true, "symbols": ["B", "H", "H", "H"], "geometry": [0.0, 0.0, 0.0, 3.30053573, 0.0, 0.0, -1.40222938, 0.0, -2.42873252, -1.2579238, 0.0, 2.17878793], "name": "BH3", "molecular_charge": 0.0, "molecular_multiplicity": 1, "fix_com": false, "fix_orientation": false, "provenance": {"creator": "QCElemental", "version": "0.28.0", "routine": "qcelemental.molparse.from_schema"}, "extras": {"notes": {}}}, "2": {"schema_name": "qcschema_molecule", "schema_version": 2, "validated": true, "symbols": ["B", "H", "H", "H"], "geometry": [0.0, 0.0, 0.0, 7.57987316, 0.0, 0.0, -1.81202355, 0.0, -3.13851685, -0.74019031, 0.0, 1.28204722], "name": "BH3", "molecular_charge": 0.0, "molecular_multiplicity": 1, "fix_com": false, "fix_orientation": false, "provenance": {"creator": "QCElemental", "version": "0.28.0", "routine": "qcelemental.molparse.from_schema"}, "extras": {"notes": {}}}, "3": {"schema_name": "qcschema_molecule", "schema_version": 2, "validated": true, "symbols": ["B", "H", "H", "H"], "geometry": [0.0, 0.0, 0.0, 1.8468011, 0.0, 0.0, -1.12009515, 0.0, -1.94006172, -2.70549407, 0.0, 4.68605319], "name": "BH3", "molecular_charge": 0.0, "molecular_multiplicity": 1, "fix_com": false, "fix_orientation": false, "provenance": {"creator": "QCElemental", "version": "0.28.0", "routine": "qcelemental.molparse.from_schema"}, "extras": {"notes": {}}}, "4": {"schema_name": "qcschema_molecule", "schema_version": 2, "validated": true, "symbols": ["B", "H", "H", "H"], "geometry": [0.0, 0.0, 0.0, 1.86234597, 0.0, 0.0, -3.77830931, 0.0, -6.5442237, -1.34762304, 0.0, 2.33415157], "name": "BH3", "molecular_charge": 0.0, "molecular_multiplicity": 1, "fix_com": false, "fix_orientation": false, "provenance": {"creator": "QCElemental", "version": "0.28.0", "routine": "qcelemental.molparse.from_schema"}, "extras": {"notes": {}}}, "5": {"schema_name": "qcschema_molecule", "schema_version": 2, "validated": true, "symbols": ["B", "H", "H", "H"], "geometry": [0.0, 0.0, 0.0, 3.03917321, 0.0, 0.0, -0.77628228, 0.0, -1.34456035, -1.12476517, 0.0, 1.94815043], "name": "BH3", "molecular_charge": 0.0, "molecular_multiplicity": 1, "fix_com": false, "fix_orientation": false, "provenance": {"creator": "QCElemental", "version": "0.28.0", "routine": "qcelemental.molparse.from_schema"}, "extras": {"notes": {}}}, "6": {"schema_name": "qcschema_molecule", "schema_version": 2, "validated": true, "symbols": ["B", "H", "H", "H"], "geometry": [0.0, 0.0, 0.0, 2.94698628, 0.0, 0.0, -2.77554659, 0.0, -4.80738772, -1.76430464, 0.0, 3.05586528], "name": "BH3", "molecular_charge": 0.0, "molecular_multiplicity": 1, "fix_com": false, "fix_orientation": false, "provenance": {"creator": "QCElemental", "version": "0.28.0", "routine": "qcelemental.molparse.from_schema"}, "extras": {"notes": {}}}, "7": {"schema_name": "qcschema_molecule", "schema_version": 2, "validated": true, "symbols": ["B", "H", "H", "H"], "geometry": [0.0, 0.0, 0.0, 2.59171738, 0.0, 0.0, -1.52246242, 0.0, -2.63698227, -1.33087605, 0.0, 2.30514494], "name": "BH3", "molecular_charge": 0.0, "molecular_multiplicity": 1, "fix_com": false, "fix_orientation": false, "provenance": {"creator": "QCElemental", "version": "0.28.0", "routine": "qcelemental.molparse.from_schema"}, "extras": {"notes": {}}}, "8": {"schema_name": "qcschema_molecule", "schema_version": 2, "validated": true, "symbols": ["B", "H", "H", "H"], "geometry": [0.0, 0.0, 0.0, 1.45179724, 0.0, 0.0, -1.30447102, 0.0, -2.25941008, -1.62355158, 0.0, 2.81207383], "name": "BH3", "molecular_charge": 0.0, "molecular_multiplicity": 1, "fix_com": false, "fix_orientation": false, "provenance": {"creator": "QCElemental", "version": "0.28.0", "routine": "qcelemental.molparse.from_schema"}, "extras": {"notes": {}}}, "9": {"schema_name": "qcschema_molecule", "schema_version": 2, "validated": true, "symbols": ["B", "H", "H", "H"], "geometry": [0.0, 0.0, 0.0, 2.34168391, 0.0, 0.0, -0.85224495, 0.0, -1.47613156, -0.9245741, 0.0, 1.60140931], "name": "BH3", "molecular_charge": 0.0, "molecular_multiplicity": 1, "fix_com": false, "fix_orientation": false, "provenance": {"creator": "QCElemental", "version": "0.28.0", "routine": "qcelemental.molparse.from_schema"}, "extras": {"notes": {}}}, "10": {"schema_name": "qcschema_molecule", "schema_version": 2, "validated": true, "symbols": ["B", "H", "H", "H"], "geometry": [0.0, 0.0, 0.0, 1.87605511, 0.0, 0.0, -0.90862546, 0.0, -1.57378546, -1.50151986, 0.0, 2.60070868], "name": "BH3", "molecular_charge": 0.0, "molecular_multiplicity": 1, "fix_com": false, "fix_orientation": false, "provenance": {"creator": "QCElemental", "version": "0.28.0", "routine": "qcelemental.molparse.from_schema"}, "extras": {"notes": {}}}, "11": {"schema_name": "qcschema_molecule", "schema_version": 2, "validated": true, "symbols": ["B", "H", "H", "H"], "geometry": [0.0, 0.0, 0.0, 1.69899007, 0.0, 0.0, -0.80975072, 0.0, -1.40252938, -1.88519989, 0.0, 3.265262], "name": "BH3", "molecular_charge": 0.0, "molecular_multiplicity": 1, "fix_com": false, "fix_orientation": false, "provenance": {"creator": "QCElemental", "version": "0.28.0", "routine": "qcelemental.molparse.from_schema"}, "extras": {"notes": {}}}, "12": {"schema_name": "qcschema_molecule", "schema_version": 2, "validated": true, "symbols": ["B", "H", "H", "H"], "geometry": [0.0, 0.0, 0.0, 1.78322554, 0.0, 0.0, -1.16208851, 0.0, -2.01279634, -1.02422089, 0.0, 1.77400262], "name": "BH3", "molecular_charge": 0.0, "molecular_multiplicity": 1, "fix_com": false, "fix_orientation": false, "provenance": {"creator": "QCElemental", "version": "0.28.0", "routine": "qcelemental.molparse.from_schema"}, "extras": {"notes": {}}}, "13": {"schema_name": "qcschema_molecule", "schema_version": 2, "validated": true, "symbols": ["B", "H", "H", "H"], "geometry": [0.0, 0.0, 0.0, 2.73073863, 0.0, 0.0, -1.56297166, 0.0, -2.70714633, -1.43968666, 0.0, 2.49361044], "name": "BH3", "molecular_charge": 0.0, "molecular_multiplicity": 1, "fix_com": false, "fix_orientation": false, "provenance": {"creator": "QCElemental", "version": "0.28.0", "routine": "qcelemental.molparse.from_schema"}, "extras": {"notes": {}}}, "14": {"schema_name": "qcschema_molecule", "schema_version": 2, "validated": true, "symbols": ["B", "H", "H", "H"], "geometry": [0.0, 0.0, 0.0, 2.46657794, 0.0, 0.0, -0.95185062, 0.0, -1.64865364, -1.28144725, 0.0, 2.21953174], "name": "BH3", "molecular_charge": 0.0, "molecular_multiplicity": 1, "fix_com": false, "fix_orientation": false, "provenance": {"creator": "QCElemental", "version": "0.28.0", "routine": "qcelemental.molparse.from_schema"}, "extras": {"notes": {}}}, "15": {"schema_name": "qcschema_molecule", "schema_version": 2, "validated": true, "symbols": ["B", "H", "H", "H"], "geometry": [0.0, 0.0, 0.0, 3.48803002, 0.0, 0.0, -1.31832037, 0.0, -2.28339787, -1.59377313, 0.0, 2.76049603], "name": "BH3", "molecular_charge": 0.0, "molecular_multiplicity": 1, "fix_com": false, "fix_orientation": false, "provenance": {"creator": "QCElemental", "version": "0.28.0", "routine": "qcelemental.molparse.from_schema"}, "extras": {"notes": {}}}, "16": {"schema_name": "qcschema_molecule", "schema_version": 2, "validated": true, "symbols": ["B", "H", "H", "H"], "geometry": [0.0, 0.0, 0.0, 2.27896618, 0.0, 0.0, -1.03144214, 0.0, -1.78651019, -1.23655548, 0.0, 2.14177691], "name": "BH3", "molecular_charge": 0.0, "molecular_multiplicity": 1, "fix_com": false, "fix_orientation": false, "provenance": {"creator": "QCElemental", "version": "0.28.0", "routine": "qcelemental.molparse.from_schema"}, "extras": {"notes": {}}}, "17": {"schema_name": "qcschema_molecule", "schema_version": 2, "validated": true, "symbols": ["B", "H", "H", "H"], "geometry": [0.0, 0.0, 0.0, 1.91587504, 0.0, 0.0, -1.85004802, 0.0, -3.20437716, -1.73428705, 0.0, 3.00387328], "name": "BH3", "molecular_charge": 0.0, "molecular_multiplicity": 1, "fix_com": false, "fix_orientation": false, "provenance": {"creator": "QCElemental", "version": "0.28.0", "routine": "qcelemental.molparse.from_schema"}, "extras": {"notes": {}}}, "18": {"schema_name": "qcschema_molecule", "schema_version": 2, "validated": true, "symbols": ["B", "H", "H", "H"], "geometry": [0.0, 0.0, 0.0, 6.52273409, 0.0, 0.0, -1.35539657, 0.0, -2.34761573, -1.56351878, 0.0, 2.70809397], "name": "BH3", "molecular_charge": 0.0, "molecular_multiplicity": 1, "fix_com": false, "fix_orientation": false, "provenance": {"creator": "QCElemental", "version": "0.28.0", "routine": "qcelemental.molparse.from_schema"}, "extras": {"notes": {}}}, "19": {"schema_name": "qcschema_molecule", "schema_version": 2, "validated": true, "symbols": ["B", "H", "H", "H"], "geometry": [0.0, 0.0, 0.0, 1.66286253, 0.0, 0.0, -1.59078448, 0.0, -2.75531954, -1.48380108, 0.0, 2.57001887], "name": "BH3", "molecular_charge": 0.0, "molecular_multiplicity": 1, "fix_com": false, "fix_orientation": false, "provenance": {"creator": "QCElemental", "version": "0.28.0", "routine": "qcelemental.molparse.from_schema"}, "extras": {"notes": {}}}, "20": {"schema_name": "qcschema_molecule", "schema_version": 2, "validated": true, "symbols": ["B", "H", "H", "H"], "geometry": [0.0, 0.0, 0.0, 5.4909615, 0.0, 0.0, -0.89235401, 0.0, -1.54560248, -1.25801712, 0.0, 2.17894958], "name": "BH3", "molecular_charge": 0.0, "molecular_multiplicity": 1, "fix_com": false, "fix_orientation": false, "provenance": {"creator": "QCElemental", "version": "0.28.0", "routine": "qcelemental.molparse.from_schema"}, "extras": {"notes": {}}}, "21": {"schema_name": "qcschema_molecule", "schema_version": 2, "validated": true, "symbols": ["B", "H", "H", "H"], "geometry": [0.0, 0.0, 0.0, 1.83911998, 0.0, 0.0, -1.8266315, 0.0, -3.16381856, -0.97601759, 0.0, 1.69051205], "name": "BH3", "molecular_charge": 0.0, "molecular_multiplicity": 1, "fix_com": false, "fix_orientation": false, "provenance": {"creator": "QCElemental", "version": "0.28.0", "routine": "qcelemental.molparse.from_schema"}, "extras": {"notes": {}}}, "22": {"schema_name": "qcschema_molecule", "schema_version": 2, "validated": true, "symbols": ["B", "H", "H", "H"], "geometry": [0.0, 0.0, 0.0, 2.76482181, 0.0, 0.0, -1.19036733, 0.0, -2.0617767, -6.48829278, 0.0, 11.23805275], "name": "BH3", "molecular_charge": 0.0, "molecular_multiplicity": 1, "fix_com": false, "fix_orientation": false, "provenance": {"creator": "QCElemental", "version": "0.28.0", "routine": "qcelemental.molparse.from_schema"}, "extras": {"notes": {}}}, "23": {"schema_name": "qcschema_molecule", "schema_version": 2, "validated": true, "symbols": ["B", "H", "H", "H"], "geometry": [0.0, 0.0, 0.0, 2.79102406, 0.0, 0.0, -1.52673614, 0.0, -2.64438456, -1.79266545, 0.0, 3.10498765], "name": "BH3", "molecular_charge": 0.0, "molecular_multiplicity": 1, "fix_com": false, "fix_orientation": false, "provenance": {"creator": "QCElemental", "version": "0.28.0", "routine": "qcelemental.molparse.from_schema"}, "extras": {"notes": {}}}, "24": {"schema_name": "qcschema_molecule", "schema_version": 2, "validated": true, "symbols": ["B", "H", "H", "H"], "geometry": [0.0, 0.0, 0.0, 2.68198606, 0.0, 0.0, -1.41416537, 0.0, -2.44940626, -3.41268017, 0.0, 5.91093545], "name": "BH3", "molecular_charge": 0.0, "molecular_multiplicity": 1, "fix_com": false, "fix_orientation": false, "provenance": {"creator": "QCElemental", "version": "0.28.0", "routine": "qcelemental.molparse.from_schema"}, "extras": {"notes": {}}}, "25": {"schema_name": "qcschema_molecule", "schema_version": 2, "validated": true, "symbols": ["B", "H", "H", "H"], "geometry": [0.0, 0.0, 0.0, 3.60132862, 0.0, 0.0, -1.59867063, 0.0, -2.76897876, -7.16642186, 0.0, 12.41260677], "name": "BH3", "molecular_charge": 0.0, "molecular_multiplicity": 1, "fix_com": false, "fix_orientation": false, "provenance": {"creator": "QCElemental", "version": "0.28.0", "routine": "qcelemental.molparse.from_schema"}, "extras": {"notes": {}}}, "26": {"schema_name": "qcschema_molecule", "schema_version": 2, "validated": true, "symbols": ["B", "H", "H", "H"], "geometry": [0.0, 0.0, 0.0, 1.521229, 0.0, 0.0, -1.1815452, 0.0, -2.04649632, -3.51882309, 0.0, 6.09478037], "name": "BH3", "molecular_charge": 0.0, "molecular_multiplicity": 1, "fix_com": false, "fix_orientation": false, "provenance": {"creator": "QCElemental", "version": "0.28.0", "routine": "qcelemental.molparse.from_schema"}, "extras": {"notes": {}}}, "27": {"schema_name": "qcschema_molecule", "schema_version": 2, "validated": true, "symbols": ["B", "H", "H", "H"], "geometry": [0.0, 0.0, 0.0, 2.27874787, 0.0, 0.0, -1.69550819, 0.0, -2.93670632, -1.01246655, 0.0, 1.75364351], "name": "BH3", "molecular_charge": 0.0, "molecular_multiplicity": 1, "fix_com": false, "fix_orientation": false, "provenance": {"creator": "QCElemental", "version": "0.28.0", "routine": "qcelemental.molparse.from_schema"}, "extras": {"notes": {}}}, "28": {"schema_name": "qcschema_molecule", "schema_version": 2, "validated": true, "symbols": ["B", "H", "H", "H"], "geometry": [0.0, 0.0, 0.0, 4.15055682, 0.0, 0.0, -1.23315369, 0.0, -2.13588484, -0.86726191, 0.0, 1.50214168], "name": "BH3", "molecular_charge": 0.0, "molecular_multiplicity": 1, "fix_com": false, "fix_orientation": false, "provenance": {"creator": "QCElemental", "version": "0.28.0", "routine": "qcelemental.molparse.from_schema"}, "extras": {"notes": {}}}, "29": {"schema_name": "qcschema_molecule", "schema_version": 2, "validated": true, "symbols": ["B", "H", "H", "H"], "geometry": [0.0, 0.0, 0.0, 2.16478479, 0.0, 0.0, -0.91801157, 0.0, -1.59004269, -0.75470492, 0.0, 1.30718726], "name": "BH3", "molecular_charge": 0.0, "molecular_multiplicity": 1, "fix_com": false, "fix_orientation": false, "provenance": {"creator": "QCElemental", "version": "0.28.0", "routine": "qcelemental.molparse.from_schema"}, "extras": {"notes": {}}}, "30": {"schema_name": "qcschema_molecule", "schema_version": 2, "validated": true, "symbols": ["B", "H", "H", "H"], "geometry": [0.0, 0.0, 0.0, 1.57480944, 0.0, 0.0, -4.30540221, 0.0, -7.45717538, -0.93858061, 0.0, 1.62566931], "name": "BH3", "molecular_charge": 0.0, "molecular_multiplicity": 1, "fix_com": false, "fix_orientation": false, "provenance": {"creator": "QCElemental", "version": "0.28.0", "routine": "qcelemental.molparse.from_schema"}, "extras": {"notes": {}}}, "31": {"schema_name": "qcschema_molecule", "schema_version": 2, "validated": true, "symbols": ["B", "H", "H", "H"], "geometry": [0.0, 0.0, 0.0, 2.29720406, 0.0, 0.0, -9.26689897, 0.0, -16.05073985, -0.98564708, 0.0, 1.70719082], "name": "BH3", "molecular_charge": 0.0, "molecular_multiplicity": 1, "fix_com": false, "fix_orientation": false, "provenance": {"creator": "QCElemental", "version": "0.28.0", "routine": "qcelemental.molparse.from_schema"}, "extras": {"notes": {}}}, "32": {"schema_name": "qcschema_molecule", "schema_version": 2, "validated": true, "symbols": ["B", "H", "H", "H"], "geometry": [0.0, 0.0, 0.0, 1.63329698, 0.0, 0.0, -1.32064554, 0.0, -2.28742518, -5.60207317, 0.0, 9.70307536], "name": "BH3", "molecular_charge": 0.0, "molecular_multiplicity": 1, "fix_com": false, "fix_orientation": false, "provenance": {"creator": "QCElemental", "version": "0.28.0", "routine": "qcelemental.molparse.from_schema"}, "extras": {"notes": {}}}, "33": {"schema_name": "qcschema_molecule", "schema_version": 2, "validated": true, "symbols": ["B", "H", "H", "H"], "geometry": [0.0, 0.0, 0.0, 2.35970637, 0.0, 0.0, -0.92423139, 0.0, -1.60081573, -2.05763951, 0.0, 3.56393618], "name": "BH3", "molecular_charge": 0.0, "molecular_multiplicity": 1, "fix_com": false, "fix_orientation": false, "provenance": {"creator": "QCElemental", "version": "0.28.0", "routine": "qcelemental.molparse.from_schema"}, "extras": {"notes": {}}}, "34": {"schema_name": "qcschema_molecule", "schema_version": 2, "validated": true, "symbols": ["B", "H", "H", "H"], "geometry": [0.0, 0.0, 0.0, 1.91897671, 0.0, 0.0, -1.39770009, 0.0, -2.42088756, -2.74524915, 0.0, 4.75491101], "name": "BH3", "molecular_charge": 0.0, "molecular_multiplicity": 1, "fix_com": false, "fix_orientation": false, "provenance": {"creator": "QCElemental", "version": "0.28.0", "routine": "qcelemental.molparse.from_schema"}, "extras": {"notes": {}}}, "35": {"schema_name": "qcschema_molecule", "schema_version": 2, "validated": true, "symbols": ["B", "H", "H", "H"], "geometry": [0.0, 0.0, 0.0, 1.95554743, 0.0, 0.0, -1.22583578, 0.0, -2.12320986, -1.14301671, 0.0, 1.97976302], "name": "BH3", "molecular_charge": 0.0, "molecular_multiplicity": 1, "fix_com": false, "fix_orientation": false, "provenance": {"creator": "QCElemental", "version": "0.28.0", "routine": "qcelemental.molparse.from_schema"}, "extras": {"notes": {}}}, "36": {"schema_name": "qcschema_molecule", "schema_version": 2, "validated": true, "symbols": ["B", "H", "H", "H"], "geometry": [0.0, 0.0, 0.0, 1.51613209, 0.0, 0.0, -1.13476225, 0.0, -1.96546587, -0.702624, 0.0, 1.21698046], "name": "BH3", "molecular_charge": 0.0, "molecular_multiplicity": 1, "fix_com": false, "fix_orientation": false, "provenance": {"creator": "QCElemental", "version": "0.28.0", "routine": "qcelemental.molparse.from_schema"}, "extras": {"notes": {}}}, "37": {"schema_name": "qcschema_molecule", "schema_version": 2, "validated": true, "symbols": ["B", "H", "H", "H"], "geometry": [0.0, 0.0, 0.0, 2.06058215, 0.0, 0.0, -1.04068033, 0.0, -1.80251121, -1.93514567, 0.0, 3.35177062], "name": "BH3", "molecular_charge": 0.0, "molecular_multiplicity": 1, "fix_com": false, "fix_orientation": false, "provenance": {"creator": "QCElemental", "version": "0.28.0", "routine": "qcelemental.molparse.from_schema"}, "extras": {"notes": {}}}, "38": {"schema_name": "qcschema_molecule", "schema_version": 2, "validated": true, "symbols": ["B", "H", "H", "H"], "geometry": [0.0, 0.0, 0.0, 2.23020866, 0.0, 0.0, -1.2935087, 0.0, -2.24042278, -0.85276073, 0.0, 1.47702491], "name": "BH3", "molecular_charge": 0.0, "molecular_multiplicity": 1, "fix_com": false, "fix_orientation": false, "provenance": {"creator": "QCElemental", "version": "0.28.0", "routine": "qcelemental.molparse.from_schema"}, "extras": {"notes": {}}}, "39": {"schema_name": "qcschema_molecule", "schema_version": 2, "validated": true, "symbols": ["B", "H", "H", "H"], "geometry": [0.0, 0.0, 0.0, 3.48735953, 0.0, 0.0, -0.88269513, 0.0, -1.52887282, -1.57744625, 0.0, 2.73221705], "name": "BH3", "molecular_charge": 0.0, "molecular_multiplicity": 1, "fix_com": false, "fix_orientation": false, "provenance": {"creator": "QCElemental", "version": "0.28.0", "routine": "qcelemental.molparse.from_schema"}, "extras": {"notes": {}}}, "40": {"schema_name": "qcschema_molecule", "schema_version": 2, "validated": true, "symbols": ["B", "H", "H", "H"], "geometry": [0.0, 0.0, 0.0, 1.6931466, 0.0, 0.0, -6.31473294, 0.0, -10.93743829, -1.49750533, 0.0, 2.59375531], "name": "BH3", "molecular_charge": 0.0, "molecular_multiplicity": 1, "fix_com": false, "fix_orientation": false, "provenance": {"creator": "QCElemental", "version": "0.28.0", "routine": "qcelemental.molparse.from_schema"}, "extras": {"notes": {}}}, "41": {"schema_name": "qcschema_molecule", "schema_version": 2, "validated": true, "symbols": ["B", "H", "H", "H"], "geometry": [0.0, 0.0, 0.0, 2.88290635, 0.0, 0.0, -1.2716686, 0.0, -2.20259463, -0.99879448, 0.0, 1.72996278], "name": "BH3", "molecular_charge": 0.0, "molecular_multiplicity": 1, "fix_com": false, "fix_orientation": false, "provenance": {"creator": "QCElemental", "version": "0.28.0", "routine": "qcelemental.molparse.from_schema"}, "extras": {"notes": {}}}, "42": {"schema_name": "qcschema_molecule", "schema_version": 2, "validated": true, "symbols": ["B", "H", "H", "H"], "geometry": [0.0, 0.0, 0.0, 12.01250253, 0.0, 0.0, -0.89070262, 0.0, -1.54274218, -0.69520564, 0.0, 1.20413149], "name": "BH3", "molecular_charge": 0.0, "molecular_multiplicity": 1, "fix_com": false, "fix_orientation": false, "provenance": {"creator": "QCElemental", "version": "0.28.0", "routine": "qcelemental.molparse.from_schema"}, "extras": {"notes": {}}}, "43": {"schema_name": "qcschema_molecule", "schema_version": 2, "validated": true, "symbols": ["B", "H", "H", "H"], "geometry": [0.0, 0.0, 0.0, 1.9152303, 0.0, 0.0, -2.61060057, 0.0, -4.52169283, -0.77693121, 0.0, 1.34568433], "name": "BH3", "molecular_charge": 0.0, "molecular_multiplicity": 1, "fix_com": false, "fix_orientation": false, "provenance": {"creator": "QCElemental", "version": "0.28.0", "routine": "qcelemental.molparse.from_schema"}, "extras": {"notes": {}}}, "44": {"schema_name": "qcschema_molecule", "schema_version": 2, "validated": true, "symbols": ["B", "H", "H", "H"], "geometry": [0.0, 0.0, 0.0, 2.11408614, 0.0, 0.0, -1.05942561, 0.0, -1.83497899, -1.6056631, 0.0, 2.78109006], "name": "BH3", "molecular_charge": 0.0, "molecular_multiplicity": 1, "fix_com": false, "fix_orientation": false, "provenance": {"creator": "QCElemental", "version": "0.28.0", "routine": "qcelemental.molparse.from_schema"}, "extras": {"notes": {}}}, "45": {"schema_name": "qcschema_molecule", "schema_version": 2, "validated": true, "symbols": ["B", "H", "H", "H"], "geometry": [0.0, 0.0, 0.0, 2.53473606, 0.0, 0.0, -1.3958577, 0.0, -2.41769645, -1.81993388, 0.0, 3.15221794], "name": "BH3", "molecular_charge": 0.0, "molecular_multiplicity": 1, "fix_com": false, "fix_orientation": false, "provenance": {"creator": "QCElemental", "version": "0.28.0", "routine": "qcelemental.molparse.from_schema"}, "extras": {"notes": {}}}, "46": {"schema_name": "qcschema_molecule", "schema_version": 2, "validated": true, "symbols": ["B", "H", "H", "H"], "geometry": [0.0, 0.0, 0.0, 2.8248933, 0.0, 0.0, -1.03817671, 0.0, -1.79817481, -2.51871088, 0.0, 4.36253521], "name": "BH3", "molecular_charge": 0.0, "molecular_multiplicity": 1, "fix_com": false, "fix_orientation": false, "provenance": {"creator": "QCElemental", "version": "0.28.0", "routine": "qcelemental.molparse.from_schema"}, "extras": {"notes": {}}}, "47": {"schema_name": "qcschema_molecule", "schema_version": 2, "validated": true, "symbols": ["B", "H", "H", "H"], "geometry": [0.0, 0.0, 0.0, 2.82492429, 0.0, 0.0, -0.84535401, 0.0, -1.46419609, -1.12471501, 0.0, 1.94806354], "name": "BH3", "molecular_charge": 0.0, "molecular_multiplicity": 1, "fix_com": false, "fix_orientation": false, "provenance": {"creator": "QCElemental", "version": "0.28.0", "routine": "qcelemental.molparse.from_schema"}, "extras": {"notes": {}}}, "48": {"schema_name": "qcschema_molecule", "schema_version": 2, "validated": true, "symbols": ["B", "H", "H", "H"], "geometry": [0.0, 0.0, 0.0, 2.16715864, 0.0, 0.0, -1.08500158, 0.0, -1.87927787, -2.2177095, 0.0, 3.84118553], "name": "BH3", "molecular_charge": 0.0, "molecular_multiplicity": 1, "fix_com": false, "fix_orientation": false, "provenance": {"creator": "QCElemental", "version": "0.28.0", "routine": "qcelemental.molparse.from_schema"}, "extras": {"notes": {}}}, "49": {"schema_name": "qcschema_molecule", "schema_version": 2, "validated": true, "symbols": ["B", "H", "H", "H"], "geometry": [0.0, 0.0, 0.0, 1.7457601, 0.0, 0.0, -0.8373985, 0.0, -1.45041674, -4.83366657, 0.0, 8.37215608], "name": "BH3", "molecular_charge": 0.0, "molecular_multiplicity": 1, "fix_com": false, "fix_orientation": false, "provenance": {"creator": "QCElemental", "version": "0.28.0", "routine": "qcelemental.molparse.from_schema"}, "extras": {"notes": {}}}}